Workbook

Sheet Data_Extraction_communication
A1: Paper_Name | B1: Paper_ID | C1: Exp_ID | D1: Treatment_ID | E1: Measure_ID | F1: Exp_ID_Cleaned | G1: ES_ID | H1: Title | I1: Authors | J1: Year | K1: Industry | L1: Venue | M1: Exp_Design | N1: Comp_Type | O1: Task_Desc | P1: Marketing_Task | Q1: Task_Data_Cleaned | R1: Task_Data_IsCategoric | S1: Task_Data_IsCode | T1: Task_Data_IsImage | U1: Task_Data_IsNumeric | V1: Task_Data_IsText | W1: Task_Data_IsVideo | X1: Task_Output | Y1: Task_Output_Cleaned | Z1: Task_Type | AA1: AI_Type | AB1: AI_Data_In | AC1: AI_Data_Out | AD1: AI_Type_Cleaned | AE1: Final_Decision | AF1: Division_Labor | AG1: Condition_Name | AH1: AI_Expl_Incl | AI1: AI_Conf_Incl | AJ1: AI_Expl_Type | AK1: Perf_Metric | AL1: Perf_Metric_Cleaned | AM1: Perf_Dir | AN1: N_Exp | AO1: N_Human | AP1: N_HumanAI | AQ1: Participant_Type | AR1: Participant_Type_2 | AS1: Participant_Source | AT1: Participant_Expert | AU1: Participant_Crowdworker | AV1: Avg_Perf_Human | AW1: Avg_Perf_AI | AX1: Avg_Perf_HumanAI | AY1: Avg_Perf_Human_Adj | AZ1: Avg_Perf_AI_Adj | BA1: Avg_Perf_HumanAI_Adj | BB1: Baseline | BC1: Avg_Perf_Baseline_Adj | BD1: Avg_Perf_Worse_Adj | BE1: Synergy | BF1: Sd_Perf_Human | BG1: Sd_Perf_AI | BH1: Sd_Perf_HumanAI | BI1: Sd_Perf_Baseline | BJ1: Sd_Perf_Worse | BK1: Est_ES | BL1: Notes | BM1: Notes_2
A2: Poursabzi-Sangdeh_2021 | B2: 5 | C2: 1 | D2: 1 | E2: 1 | F2: 5.1 | G2: 5.1.1.1 | H2: Manipulating and Measuring Model Interpretability | I2: Poursabzi-Sangdeh, Forough; Goldstein, Daniel G; Hofman, Jake M; Wortman Vaughan, Jennifer Wortman; Wallach, Hanna | J2: 2021 | K2: Business | L2: Proceedings of the 2021 CHI Conference on Human Factors in Computing Systems | M2: Mixed, Between-Subjects | N2: Independent Samples | O2: Predict housing prices | P2: =VLOOKUP(O2,Sheet3!$A$1:$B$22,2,0) -> Demand Forecasting | Q2: Numeric | R2: No | S2: No | T2: No | U2: Yes | V2: No | W2: No | X2: Numeric | Y2: Numeric | Z2: Decide | AA2: Shallow | AB2: Numeric | AC2: Numeric | AD2: Rule-Based | AE2: Human | AF2: No | AG2: HAI = BB-2 | AH2: No | AI2: No | AK2: Prediction Error | AL2: Error | AM2: Down | AN2: 1250 | AO2: 252 | AP2: 247 | AQ2: Crowdworkers | AR2: Crowdworkers | AS2: MTurk | AT2: No | AU2: Yes | AV2: 330555 | AW2: 180000 | AX2: 232267 | AY2: -330555 | AZ2: -180000 | BA2: -232267 | BB2: AI | BC2: -180000 | BD2: -330555 | BE2: 0 | BF2: 122515 | BG2: 0 | BH2: 56580 | BI2: 0 | BJ2: 122515 | BK2: No | BL2: HAI = BB-2
A3: Poursabzi-Sangdeh_2021 | B3: 5 | C3: 1 | D3: 2 | E3: 1 | F3: 5.1 | G3: 5.1.2.1 | H3: Manipulating and Measuring Model Interpretability | I3: Poursabzi-Sangdeh, Forough; Goldstein, Daniel G; Hofman, Jake M; Wortman Vaughan, Jennifer Wortman; Wallach, Hanna | J3: 2021 | K3: Business | L3: Proceedings of the 2021 CHI Conference on Human Factors in Computing Systems | M3: Mixed, Between-Subjects | N3: Independent Samples | O3: Predict housing prices | P3: =VLOOKUP(O3,Sheet3!$A$1:$B$22,2,0) -> Demand Forecasting | Q3: Numeric | R3: No | S3: No | T3: No | U3: Yes | V3: No | W3: No | X3: Numeric | Y3: Numeric | Z3: Decide | AA3: Shallow | AB3: Numeric | AC3: Numeric | AD3: Rule-Based | AE3: Human | AF3: No | AG3: HAI = BB-8 | AH3: No | AI3: No | AK3: Prediction Error | AL3: Error | AM3: Down | AN3: 1250 | AO3: 252 | AP3: 256 | AQ3: Crowdworkers | AR3: Crowdworkers | AS3: MTurk | AT3: No | AU3: Yes | AV3: 330555 | AW3: 180000 | AX3: 234453 | AY3: -330555 | AZ3: -180000 | BA3: -234453 | BB3: AI | BC3: -180000 | BD3: -330555 | BE3: 0 | BF3: 122515 | BG3: 0 | BH3: 77178 | BI3: 0 | BJ3: 122515 | BK3: No | BL3: HAI = BB-8
A4: Poursabzi-Sangdeh_2021 | B4: 5 | C4: 1 | D4: 3 | E4: 1 | F4: 5.1 | G4: 5.1.3.1 | H4: Manipulating and Measuring Model Interpretability | I4: Poursabzi-Sangdeh, Forough; Goldstein, Daniel G; Hofman, Jake M; Wortman Vaughan, Jennifer Wortman; Wallach, Hanna | J4: 2021 | K4: Business | L4: Proceedings of the 2021 CHI Conference on Human Factors in Computing Systems | M4: Mixed, Between-Subjects | N4: Independent Samples | O4: Predict housing prices | P4: =VLOOKUP(O4,Sheet3!$A$1:$B$22,2,0) -> Demand Forecasting | Q4: Numeric | R4: No | S4: No | T4: No | U4: Yes | V4: No | W4: No | X4: Numeric | Y4: Numeric | Z4: Decide | AA4: Shallow | AB4: Numeric | AC4: Numeric | AD4: Rule-Based | AE4: Human | AF4: No | AG4: HAI = CLEAR-2 | AH4: Yes | AI4: No | AJ4: Image, Numeric | AK4: Prediction Error | AL4: Error | AM4: Down | AN4: 1250 | AO4: 252 | AP4: 248 | AQ4: Crowdworkers | AR4: Crowdworkers | AS4: MTurk | AT4: No | AU4: Yes | AV4: 330555 | AW4: 180000 | AX4: 232943 | AY4: -330555 | AZ4: -180000 | BA4: -232943 | BB4: AI | BC4: -180000 | BD4: -330555 | BE4: 0 | BF4: 122515 | BG4: 0 | BH4: 81889 | BI4: 0 | BJ4: 122515 | BK4: No | BL4: HAI = CLEAR-2
A5: Poursabzi-Sangdeh_2021 | B5: 5 | C5: 1 | D5: 4 | E5: 1 | F5: 5.1 | G5: 5.1.4.1 | H5: Manipulating and Measuring Model Interpretability | I5: Poursabzi-Sangdeh, Forough; Goldstein, Daniel G; Hofman, Jake M; Wortman Vaughan, Jennifer Wortman; Wallach, Hanna | J5: 2021 | K5: Business | L5: Proceedings of the 2021 CHI Conference on Human Factors in Computing Systems | M5: Mixed, Between-Subjects | N5: Independent Samples | O5: Predict housing prices | P5: =VLOOKUP(O5,Sheet3!$A$1:$B$22,2,0) -> Demand Forecasting | Q5: Numeric | R5: No | S5: No | T5: No | U5: Yes | V5: No | W5: No | X5: Numeric | Y5: Numeric | Z5: Decide | AA5: Shallow | AB5: Numeric | AC5: Numeric | AD5: Rule-Based | AE5: Human | AF5: No | AG5: HAI = CLEAR-8 | AH5: Yes | AI5: No | AJ5: Image, Numeric | AK5: Prediction Error | AL5: Error | AM5: Down | AN5: 1250 | AO5: 252 | AP5: 247 | AQ5: Crowdworkers | AR5: Crowdworkers | AS5: MTurk | AT5: No | AU5: Yes | AV5: 330555 | AW5: 180000 | AX5: 248016 | AY5: -330555 | AZ5: -180000 | BA5: -248016 | BB5: AI | BC5: -180000 | BD5: -330555 | BE5: 0 | BF5: 122515 | BG5: 0 | BH5: 82411 | BI5: 0 | BJ5: 122515 | BK5: No | BL5: HAI = CLEAR-8
A6: Poursabzi-Sangdeh_2021 | B6: 5 | C6: 2 | D6: 1 | E6: 1 | F6: 5.2 | G6: 5.2.1.1 | H6: Manipulating and Measuring Model Interpretability | I6: Poursabzi-Sangdeh, Forough; Goldstein, Daniel G; Hofman, Jake M; Wortman Vaughan, Jennifer Wortman; Wallach, Hanna | J6: 2021 | K6: Business | L6: Proceedings of the 2021 CHI Conference on Human Factors in Computing Systems | M6: Mixed, Between-Subjects | N6: Independent Samples | O6: Predict housing prices | P6: =VLOOKUP(O6,Sheet3!$A$1:$B$22,2,0) -> Demand Forecasting | Q6: Numeric | R6: No | S6: No | T6: No | U6: Yes | V6: No | W6: No | X6: Numeric | Y6: Numeric | Z6: Decide | AA6: Shallow | AB6: Numeric | AC6: Numeric | AD6: Rule-Based | AE6: Human | AF6: No | AG6: HAI = BB-2 | AH6: No | AI6: No | AK6: Prediction Error | AL6: Error | AM6: Down | AN6: 750 | AO6: 152 | AP6: 147 | AQ6: Crowdworkers | AR6: Crowdworkers | AS6: MTurk | AT6: No | AU6: Yes | AV6: 31145 | AW6: 18000 | AX6: 22864 | AY6: -31145 | AZ6: -18000 | BA6: -22864 | BB6: AI | BC6: -18000 | BD6: -31145 | BE6: 0 | BF6: 11303 | BG6: 0 | BH6: 5927 | BI6: 0 | BJ6: 11303 | BK6: No | BL6: HAI = BB-2
A7: Poursabzi-Sangdeh_2021 | B7: 5 | C7: 2 | D7: 2 | E7: 1 | F7: 5.2 | G7: 5.2.2.1 | H7: Manipulating and Measuring Model Interpretability | I7: Poursabzi-Sangdeh, Forough; Goldstein, Daniel G; Hofman, Jake M; Wortman Vaughan, Jennifer Wortman; Wallach, Hanna | J7: 2021 | K7: Business | L7: Proceedings of the 2021 CHI Conference on Human Factors in Computing Systems | M7: Mixed, Between-Subjects | N7: Independent Samples | O7: Predict housing prices | P7: =VLOOKUP(O7,Sheet3!$A$1:$B$22,2,0) -> Demand Forecasting | Q7: Numeric | R7: No | S7: No | T7: No | U7: Yes | V7: No | W7: No | X7: Numeric | Y7: Numeric | Z7: Decide | AA7: Shallow | AB7: Numeric | AC7: Numeric | AD7: Rule-Based | AE7: Human | AF7: No | AG7: HAI = BB-8 | AH7: No | AI7: No | AK7: Prediction Error | AL7: Error | AM7: Down | AN7: 750 | AO7: 152 | AP7: 151 | AQ7: Crowdworkers | AR7: Crowdworkers | AS7: MTurk | AT7: No | AU7: Yes | AV7: 31145 | AW7: 18000 | AX7: 23053 | AY7: -31145 | AZ7: -18000 | BA7: -23053 | BB7: AI | BC7: -18000 | BD7: -31145 | BE7: 0 | BF7: 11303 | BG7: 0 | BH7: 6341 | BI7: 0 | BJ7: 11303 | BK7: No | BL7: HAI = BB-8
A8: Poursabzi-Sangdeh_2021 | B8: 5 | C8: 2 | D8: 3 | E8: 1 | F8: 5.2 | G8: 5.2.3.1 | H8: Manipulating and Measuring Model Interpretability | I8: Poursabzi-Sangdeh, Forough; Goldstein, Daniel G; Hofman, Jake M; Wortman Vaughan, Jennifer Wortman; Wallach, Hanna | J8: 2021 | K8: Business | L8: Proceedings of the 2021 CHI Conference on Human Factors in Computing Systems | M8: Mixed, Between-Subjects | N8: Independent Samples | O8: Predict housing prices | P8: =VLOOKUP(O8,Sheet3!$A$1:$B$22,2,0) -> Demand Forecasting | Q8: Numeric | R8: No | S8: No | T8: No | U8: Yes | V8: No | W8: No | X8: Numeric | Y8: Numeric | Z8: Decide | AA8: Shallow | AB8: Numeric | AC8: Numeric | AD8: Rule-Based | AE8: Human | AF8: No | AG8: HAI = CLEAR-2 | AH8: Yes | AI8: No | AJ8: Image, Numeric | AK8: Prediction Error | AL8: Error | AM8: Down | AN8: 750 | AO8: 152 | AP8: 150 | AQ8: Crowdworkers | AR8: Crowdworkers | AS8: MTurk | AT8: No | AU8: Yes | AV8: 31145 | AW8: 18000 | AX8: 21760 | AY8: -31145 | AZ8: -18000 | BA8: -21760 | BB8: AI | BC8: -18000 | BD8: -31145 | BE8: 0 | BF8: 11303 | BG8: 0 | BH8: 6597 | BI8: 0 | BJ8: 11303 | BK8: No | BL8: HAI = CLEAR-2
A9: Poursabzi-Sangdeh_2021 | B9: 5 | C9: 2 | D9: 4 | E9: 1 | F9: 5.2 | G9: 5.2.4.1 | H9: Manipulating and Measuring Model Interpretability | I9: Poursabzi-Sangdeh, Forough; Goldstein, Daniel G; Hofman, Jake M; Wortman Vaughan, Jennifer Wortman; Wallach, Hanna | J9: 2021 | K9: Business | L9: Proceedings of the 2021 CHI Conference on Human Factors in Computing Systems | M9: Mixed, Between-Subjects | N9: Independent Samples | O9: Predict housing prices | P9: =VLOOKUP(O9,Sheet3!$A$1:$B$22,2,0) -> Demand Forecasting | Q9: Numeric | R9: No | S9: No | T9: No | U9: Yes | V9: No | W9: No | X9: Numeric | Y9: Numeric | Z9: Decide | AA9: Shallow | AB9: Numeric | AC9: Numeric | AD9: Rule-Based | AE9: Human | AF9: No | AG9: HAI = CLEAR-8 | AH9: Yes | AI9: No | AJ9: Image, Numeric | AK9: Prediction Error | AL9: Error | AM9: Down | AN9: 750 | AO9: 152 | AP9: 150 | AQ9: Crowdworkers | AR9: Crowdworkers | AS9: MTurk | AT9: No | AU9: Yes | AV9: 31145 | AW9: 18000 | AX9: 25727 | AY9: -31145 | AZ9: -18000 | BA9: -25727 | BB9: AI | BC9: -18000 | BD9: -31145 | BE9: 0 | BF9: 11303 | BG9: 0 | BH9: 8860 | BI9: 0 | BJ9: 11303 | BK9: No | BL9: HAI = CLEAR-8
A10: Poursabzi-Sangdeh_2021 | B10: 5 | C10: 3 | D10: 1 | E10: 1 | F10: 5.3 | G10: 5.3.1.1 | H10: Manipulating and Measuring Model Interpretability | I10: Poursabzi-Sangdeh, Forough; Goldstein, Daniel G; Hofman, Jake M; Wortman Vaughan, Jennifer Wortman; Wallach, Hanna | J10: 2021 | K10: Business | L10: Proceedings of the 2021 CHI Conference on Human Factors in Computing Systems | M10: Mixed, Within-Subjects | N10: Dependent Samples | O10: Predict housing prices | P10: =VLOOKUP(O10,Sheet3!$A$1:$B$22,2,0) -> Demand Forecasting | Q10: Numeric | R10: No | S10: No | T10: No | U10: Yes | V10: No | W10: No | X10: Numeric | Y10: Numeric | Z10: Decide | AA10: Shallow | AB10: Numeric | AC10: Numeric | AD10: Rule-Based | AE10: Human | AF10: No | AG10: HAI = BB-2 | AH10: No | AI10: No | AK10: Prediction Error | AL10: Error | AM10: Down | AN10: 803 | AO10: 202 | AP10: 202 | AQ10: Crowdworkers | AR10: Crowdworkers | AS10: MTurk | AT10: No | AU10: Yes | AV10: 322426 | AW10: 180000 | AX10: 226436 | AY10: -322426 | AZ10: -180000 | BA10: -226436 | BB10: AI | BC10: -180000 | BD10: -322426 | BE10: 0 | BF10: 121858 | BG10: 0 | BH10: 77781 | BI10: 0 | BJ10: 121858 | BK10: No | BL10: HAI = BB-2
A11: Poursabzi-Sangdeh_2021 | B11: 5 | C11: 3 | D11: 2 | E11: 1 | F11: 5.3 | G11: 5.3.2.1 | H11: Manipulating and Measuring Model Interpretability | I11: Poursabzi-Sangdeh, Forough; Goldstein, Daniel G; Hofman, Jake M; Wortman Vaughan, Jennifer Wortman; Wallach, Hanna | J11: 2021 | K11: Business | L11: Proceedings of the 2021 CHI Conference on Human Factors in Computing Systems | M11: Mixed, Within-Subjects | N11: Dependent Samples | O11: Predict housing prices | P11: =VLOOKUP(O11,Sheet3!$A$1:$B$22,2,0) -> Demand Forecasting | Q11: Numeric | R11: No | S11: No | T11: No | U11: Yes | V11: No | W11: No | X11: Numeric | Y11: Numeric | Z11: Decide | AA11: Shallow | AB11: Numeric | AC11: Numeric | AD11: Rule-Based | AE11: Human | AF11: No | AG11: HAI = BB-8 | AH11: No | AI11: No | AK11: Prediction Error | AL11: Error | AM11: Down | AN11: 803 | AO11: 200 | AP11: 200 | AQ11: Crowdworkers | AR11: Crowdworkers | AS11: MTurk | AT11: No | AU11: Yes | AV11: 324141 | AW11: 180000 | AX11: 217980 | AY11: -324141 | AZ11: -180000 | BA11: -217980 | BB11: AI | BC11: -180000 | BD11: -324141 | BE11: 0 | BF11: 109289 | BG11: 0 | BH11: 64729 | BI11: 0 | BJ11: 109289 | BK11: No | BL11: HAI = BB-8
A12: Poursabzi-Sangdeh_2021 | B12: 5 | C12: 3 | D12: 3 | E12: 1 | F12: 5.3 | G12: 5.3.3.1 | H12: Manipulating and Measuring Model Interpretability | I12: Poursabzi-Sangdeh, Forough; Goldstein, Daniel G; Hofman, Jake M; Wortman Vaughan, Jennifer Wortman; Wallach, Hanna | J12: 2021 | K12: Business | L12: Proceedings of the 2021 CHI Conference on Human Factors in Computing Systems | M12: Mixed, Within-Subjects | N12: Dependent Samples | O12: Predict housing prices | P12: =VLOOKUP(O12,Sheet3!$A$1:$B$22,2,0) -> Demand Forecasting | Q12: Numeric | R12: No | S12: No | T12: No | U12: Yes | V12: No | W12: No | X12: Numeric | Y12: Numeric | Z12: Decide | AA12: Shallow | AB12: Numeric | AC12: Numeric | AD12: Rule-Based | AE12: Human | AF12: No | AG12: HAI = CLEAR-2 | AH12: Yes | AI12: No | AJ12: Image, Numeric | AK12: Prediction Error | AL12: Error | AM12: Down | AN12: 803 | AO12: 202 | AP12: 202 | AQ12: Crowdworkers | AR12: Crowdworkers | AS12: MTurk | AT12: No | AU12: Yes | AV12: 307277 | AW12: 180000 | AX12: 221535 | AY12: -307277 | AZ12: -180000 | BA12: -221535 | BB12: AI | BC12: -180000 | BD12: -307277 | BE12: 0 | BF12: 110692 | BG12: 0 | BH12: 67183 | BI12: 0 | BJ12: 110692 | BK12: No | BL12: HAI = CLEAR-2
A13: Poursabzi-Sangdeh_2021 | B13: 5 | C13: 3 | D13: 4 | E13: 1 | F13: 5.3 | G13: 5.3.4.1 | H13: Manipulating and Measuring Model Interpretability | I13: Poursabzi-Sangdeh, Forough; Goldstein, Daniel G; Hofman, Jake M; Wortman Vaughan, Jennifer Wortman; Wallach, Hanna | J13: 2021 | K13: Business | L13: Proceedings of the 2021 CHI Conference on Human Factors in Computing Systems | M13: Mixed, Within-Subjects | N13: Dependent Samples | O13: Predict housing prices | P13: =VLOOKUP(O13,Sheet3!$A$1:$B$22,2,0) -> Demand Forecasting | Q13: Numeric | R13: No | S13: No | T13: No | U13: Yes | V13: No | W13: No | X13: Numeric | Y13: Numeric | Z13: Decide | AA13: Shallow | AB13: Numeric | AC13: Numeric | AD13: Rule-Based | AE13: Human | AF13: No | AG13: HAI = CLEAR-8 | AH13: Yes | AI13: No | AJ13: Image, Numeric | AK13: Prediction Error | AL13: Error | AM13: Down | AN13: 803 | AO13: 198 | AP13: 198 | AQ13: Crowdworkers | AR13: Crowdworkers | AS13: MTurk | AT13: No | AU13: Yes | AV13: 328950 | AW13: 180000 | AX13: 220850 | AY13: -328950 | AZ13: -180000 | BA13: -220850 | BB13: AI | BC13: -180000 | BD13: -328950 | BE13: 0 | BF13: 114314 | BG13: 0 | BH13: 56335 | BI13: 0 | BJ13: 114314 | BK13: No | BL13: HAI = CLEAR-8
A14: Bansal_2021 | B14: 6 | C14: 3 | D14: 1 | E14: 1 | F14: 6.3 | G14: 6.3.1.1 | H14: Does the Whole Exceed Its Parts? The Effect of AI Explanations on Complementary Team Performance | I14: Bansal, Gagan; Wu, Tongshuang; Zhou, Joyce; Fok, Raymond; Nushi, Besmira; Kamar, Ece; Ribeiro, Marco Tulio; Weld, Daniel | J14: 2021 | K14: Business | L14: Proceedings of the 2021 CHI Conference on Human Factors in Computing Systems | M14: Between-Subjects | N14: Independent Samples | O14: Answer LSAT questions | P14: =VLOOKUP(O14,Sheet3!$A$1:$B$22,2,0) -> Customer Service | Q14: Text | R14: No | S14: No | T14: No | U14: No | V14: Yes | W14: No | X14: Categoric | Y14: Categoric | Z14: Decide | AA14: Deep | AB14: Text | AC14: Categorical | AD14: Deep | AE14: Human | AF14: No | AG14: HAI = LSAT, Conf | AH14: Yes | AI14: Yes | AJ14: Numeric | AK14: Accuracy | AL14: Accuracy | AM14: Up | AN14: 507 | AO14: 100 | AP14: 102 | AQ14: Crowdworkers | AR14: Crowdworkers | AS14: MTurk | AT14: No | AU14: Yes | AV14: 0.5815 | AW14: 0.65 | AX14: 0.698 | AY14: 0.5815 | AZ14: 0.65 | BA14: 0.698 | BB14: AI | BC14: 0.65 | BD14: 0.5815 | BE14: 1 | BF14: 0.165 | BG14: 0 | BH14: 0.1391 | BI14: 0 | BJ14: 0.165 | BK14: No | BL14: HAI = Conf
A15: Bansal_2021 | B15: 6 | C15: 3 | D15: 2 | E15: 1 | F15: 6.3 | G15: 6.3.2.1 | H15: Does the Whole Exceed Its Parts? The Effect of AI Explanations on Complementary Team Performance | I15: Bansal, Gagan; Wu, Tongshuang; Zhou, Joyce; Fok, Raymond; Nushi, Besmira; Kamar, Ece; Ribeiro, Marco Tulio; Weld, Daniel | J15: 2021 | K15: Business | L15: Proceedings of the 2021 CHI Conference on Human Factors in Computing Systems | M15: Between-Subjects | N15: Independent Samples | O15: Answer LSAT questions | P15: =VLOOKUP(O15,Sheet3!$A$1:$B$22,2,0) -> Customer Service | Q15: Text | R15: No | S15: No | T15: No | U15: No | V15: Yes | W15: No | X15: Categoric | Y15: Categoric | Z15: Decide | AA15: Deep | AB15: Text | AC15: Categorical | AD15: Deep | AE15: Human | AF15: No | AG15: HAI = LSAT, Explain-Top-1 | AH15: Yes | AI15: Yes | AJ15: Image, Numeric, Text | AK15: Accuracy | AL15: Accuracy | AM15: Up | AN15: 507 | AO15: 100 | AP15: 101 | AQ15: Crowdworkers | AR15: Crowdworkers | AS15: MTurk | AT15: No | AU15: Yes | AV15: 0.5815 | AW15: 0.65 | AX15: 0.6901 | AY15: 0.5815 | AZ15: 0.65 | BA15: 0.6901 | BB15: AI | BC15: 0.65 | BD15: 0.5815 | BE15: 1 | BF15: 0.165 | BG15: 0 | BH15: 0.1303 | BI15: 0 | BJ15: 0.165 | BK15: No | BL15: HAI = Explain-Top-1
A16: Bansal_2021 | B16: 6 | C16: 3 | D16: 3 | E16: 1 | F16: 6.3 | G16: 6.3.3.1 | H16: Does the Whole Exceed Its Parts? The Effect of AI Explanations on Complementary Team Performance | I16: Bansal, Gagan; Wu, Tongshuang; Zhou, Joyce; Fok, Raymond; Nushi, Besmira; Kamar, Ece; Ribeiro, Marco Tulio; Weld, Daniel | J16: 2021 | K16: Business | L16: Proceedings of the 2021 CHI Conference on Human Factors in Computing Systems | M16: Between-Subjects | N16: Independent Samples | O16: Answer LSAT questions | P16: =VLOOKUP(O16,Sheet3!$A$1:$B$22,2,0) -> Customer Service | Q16: Text | R16: No | S16: No | T16: No | U16: No | V16: Yes | W16: No | X16: Categoric | Y16: Categoric | Z16: Decide | AA16: Deep | AB16: Text | AC16: Categorical | AD16: Deep | AE16: Human | AF16: No | AG16: HAI = LSAT, Explain-Top-2 | AH16: Yes | AI16: Yes | AJ16: Image, Numeric, Text | AK16: Accuracy | AL16: Accuracy | AM16: Up | AN16: 507 | AO16: 100 | AP16: 103 | AQ16: Crowdworkers | AR16: Crowdworkers | AS16: MTurk | AT16: No | AU16: Yes | AV16: 0.5815 | AW16: 0.65 | AX16: 0.6816 | AY16: 0.5815 | AZ16: 0.65 | BA16: 0.6816 | BB16: AI | BC16: 0.65 | BD16: 0.5815 | BE16: 1 | BF16: 0.165 | BG16: 0 | BH16: 0.1298 | BI16: 0 | BJ16: 0.165 | BK16: No | BL16: HAI = Explain-Top-2
A17: Bansal_2021 | B17: 6 | C17: 3 | D17: 4 | E17: 1 | F17: 6.3 | G17: 6.3.4.1 | H17: Does the Whole Exceed Its Parts? The Effect of AI Explanations on Complementary Team Performance | I17: Bansal, Gagan; Wu, Tongshuang; Zhou, Joyce; Fok, Raymond; Nushi, Besmira; Kamar, Ece; Ribeiro, Marco Tulio; Weld, Daniel | J17: 2021 | K17: Business | L17: Proceedings of the 2021 CHI Conference on Human Factors in Computing Systems | M17: Between-Subjects | N17: Independent Samples | O17: Answer LSAT questions | P17: =VLOOKUP(O17,Sheet3!$A$1:$B$22,2,0) -> Customer Service | Q17: Text | R17: No | S17: No | T17: No | U17: No | V17: Yes | W17: No | X17: Categoric | Y17: Categoric | Z17: Decide | AA17: Deep | AB17: Text | AC17: Categorical | AD17: Deep | AE17: Human | AF17: No | AG17: HAI = LSAT, Adaptive | AH17: Yes | AI17: Yes | AJ17: Image, Numeric, Text | AK17: Accuracy | AL17: Accuracy | AM17: Up | AN17: 507 | AO17: 100 | AP17: 101 | AQ17: Crowdworkers | AR17: Crowdworkers | AS17: MTurk | AT17: No | AU17: Yes | AV17: 0.5815 | AW17: 0.65 | AX17: 0.701 | AY17: 0.5815 | AZ17: 0.65 | BA17: 0.701 | BB17: AI | BC17: 0.65 | BD17: 0.5815 | BE17: 1 | BF17: 0.165 | BG17: 0 | BH17: 0.1204 | BI17: 0 | BJ17: 0.165 | BK17: No | BL17: HAI = Adaptive
A18: Kyriacou_2021 | B18: 7 | C18: 1 | D18: 2 | E18: 1 | F18: 7.1 | G18: 7.1.2.1 | H18: Learning to Work in a Materials Recovery Facility: Can Humans and Machines Learn from Each Other? | I18: Kyriacou, Harrison; Ramakrishnan, Anand; Whitehill, Jacob | J18: 2021 | K18: Business | L18: LAK21: 11th International Learning Analytics and Knowledge Conference | M18: Between-Subjects | N18: Independent Samples | O18: Sort recyclables | P18: =VLOOKUP(O18,Sheet3!$A$1:$B$22,2,0) -> Review Analysis | Q18: Image | R18: No | S18: No | T18: Yes | U18: No | V18: No | W18: No | X18: Binary | Y18: Binary | Z18: Decide | AA18: Deep | AB18: Image | AC18: Image | AD18: Deep | AE18: Human | AF18: No | AG18: HAI = P-P-N, Round 2 | AH18: No | AI18: No | AK18: Score | AL18: Score | AM18: Up | AN18: 33 | AO18: 21 | AP18: 12 | AQ18: Crowdworkers | AR18: Crowdworkers | AS18: MTurk | AT18: No | AU18: Yes | AV18: 60.08 | AW18: 100 | AX18: 89.67 | AY18: 60.08 | AZ18: 100 | BA18: 89.67 | BB18: AI | BC18: 100 | BD18: 60.08 | BE18: 0 | BF18: 26.44 | BG18: 0 | BH18: 14.19 | BI18: 0 | BJ18: 26.44 | BK18: No | BL18: HAI = P-P-N, Round 2
A19: Liu_2021 | B19: 9 | C19: 2 | D19: 1 | E19: 1 | F19: 9.2 | G19: 9.2.1.1 | H19: Understanding the Effect of Out-of-Distribution Examples and Interactive Explanations on Human-AI Decision Making | I19: Liu, Han; Lai, Vivian; Tan, Chenhao | J19: 2021 | K19: Business | L19: Proc. ACM Hum.-Comput. Interact. | M19: Between-Subjects | N19: Independent Samples | O19: Predict a person's profession | P19: Customer Segmentation | Q19: Text | R19: No | S19: No | T19: No | U19: No | V19: Yes | W19: No | X19: Categoric | Y19: Categoric | Z19: Decide | AA19: Shallow | AB19: Text | AC19: Categorical | AD19: Rule-Based | AE19: Human | AF19: No | AG19: BIOS, IND, H = None/None, HAI = Static/Static | AH19: Yes | AI19: No | AJ19: Image, Numeric, Text | AK19: Accuracy | AL19: Accuracy | AM19: Up | AN19: 1296 | AO19: 216 | AP19: 216 | AQ19: Crowdworkers | AR19: Crowdworkers | AS19: MTurk | AT19: No | AU19: Yes | AV19: 0.635 | AW19: 0.841 | AX19: 0.734 | AY19: 0.635 | AZ19: 0.841 | BA19: 0.734 | BB19: AI | BC19: 0.841 | BD19: 0.635 | BE19: 0 | BF19: 0.156 | BG19: 0 | BH19: 0.134 | BI19: 0 | BJ19: 0.156 | BK19: No | BL19: WikiAttack, HAI = Predicted labels
A20: Liu_2021 | B20: 9 | C20: 2 | D20: 2 | E20: 1 | F20: 9.2 | G20: 9.2.2.1 | H20: Understanding the Effect of Out-of-Distribution Examples and Interactive Explanations on Human-AI Decision Making | I20: Liu, Han; Lai, Vivian; Tan, Chenhao | J20: 2021 | K20: Business | L20: Proc. ACM Hum.-Comput. Interact. | M20: Between-Subjects | N20: Independent Samples | O20: Predict a person's profession | P20: Customer Segmentation | Q20: Text | R20: No | S20: No | T20: No | U20: No | V20: Yes | W20: No | X20: Categoric | Y20: Categoric | Z20: Decide | AA20: Shallow | AB20: Text | AC20: Categorical | AD20: Rule-Based | AE20: Human | AF20: No | AG20: BIOS, IND, H = None/None, HAI = Inter/Inter | AH20: Yes | AI20: No | AJ20: Image, Numeric, Text | AK20: Accuracy | AL20: Accuracy | AM20: Up | AN20: 1296 | AO20: 216 | AP20: 216 | AQ20: Crowdworkers | AR20: Crowdworkers | AS20: MTurk | AT20: No | AU20: Yes | AV20: 0.635 | AW20: 0.841 | AX20: 0.724 | AY20: 0.635 | AZ20: 0.841 | BA20: 0.724 | BB20: AI | BC20: 0.841 | BD20: 0.635 | BE20: 0 | BF20: 0.156 | BG20: 0 | BH20: 0.139 | BI20: 0 | BJ20: 0.156 | BK20: No | BL20: WikiAttack, HAI = Predicted labels + local explanations
A21: Liu_2021 | B21: 9 | C21: 2 | D21: 3 | E21: 1 | F21: 9.2 | G21: 9.2.3.1 | H21: Understanding the Effect of Out-of-Distribution Examples and Interactive Explanations on Human-AI Decision Making | I21: Liu, Han; Lai, Vivian; Tan, Chenhao | J21: 2021 | K21: Business | L21: Proc. ACM Hum.-Comput. Interact. | M21: Between-Subjects | N21: Independent Samples | O21: Predict a person's profession | P21: Customer Segmentation | Q21: Text | R21: No | S21: No | T21: No | U21: No | V21: Yes | W21: No | X21: Categoric | Y21: Categoric | Z21: Decide | AA21: Shallow | AB21: Text | AC21: Categorical | AD21: Rule-Based | AE21: Human | AF21: No | AG21: BIOS, OOD, H = None/None, HAI = Static/Static | AH21: Yes | AI21: No | AJ21: Image, Numeric, Text | AK21: Accuracy | AL21: Accuracy | AM21: Up | AN21: 1296 | AO21: 216 | AP21: 216 | AQ21: Crowdworkers | AR21: Crowdworkers | AS21: MTurk | AT21: No | AU21: Yes | AV21: 0.684 | AW21: 0.766 | AX21: 0.735 | AY21: 0.684 | AZ21: 0.766 | BA21: 0.735 | BB21: AI | BC21: 0.766 | BD21: 0.684 | BE21: 0 | BF21: 0.177 | BG21: 0 | BH21: 0.102 | BI21: 0 | BJ21: 0.177 | BK21: No | BL21: WikiAttack, HAI = Predicted labels + local explanations + global explanations
A22: Liu_2021 | B22: 9 | C22: 2 | D22: 4 | E22: 1 | F22: 9.2 | G22: 9.2.4.1 | H22: Understanding the Effect of Out-of-Distribution Examples and Interactive Explanations on Human-AI Decision Making | I22: Liu, Han; Lai, Vivian; Tan, Chenhao | J22: 2021 | K22: Business | L22: Proc. ACM Hum.-Comput. Interact. | M22: Between-Subjects | N22: Independent Samples | O22: Predict a person's profession | P22: Customer Segmentation | Q22: Text | R22: No | S22: No | T22: No | U22: No | V22: Yes | W22: No | X22: Categoric | Y22: Categoric | Z22: Decide | AA22: Shallow | AB22: Text | AC22: Categorical | AD22: Rule-Based | AE22: Human | AF22: No | AG22: BIOS, OOD, H = None/None, HAI = Inter/Inter | AH22: Yes | AI22: No | AJ22: Image, Numeric, Text | AK22: Accuracy | AL22: Accuracy | AM22: Up | AN22: 1296 | AO22: 216 | AP22: 216 | AQ22: Crowdworkers | AR22: Crowdworkers | AS22: MTurk | AT22: No | AU22: Yes | AV22: 0.684 | AW22: 0.766 | AX22: 0.728 | AY22: 0.684 | AZ22: 0.766 | BA22: 0.728 | BB22: AI | BC22: 0.766 | BD22: 0.684 | BE22: 0 | BF22: 0.177 | BG22: 0 | BH22: 0.13 | BI22: 0 | BJ22: 0.177 | BK22: No | BL22: Reddit, HAI = Predicted labels
A23: Ma_2023 | B23: 14 | C23: 1 | D23: 1 | E23: 1 | F23: 14.1 | G23: 14.1.1.1 | H23: Who Should I Trust: AI or Myself? Leveraging Human and AI Correctness Likelihood to Promote Appropriate Trust in AI-Assisted Decision-Making | I23: Ma, Shuai; Lei, Ying; Wang, Xinru; Zheng, Chengbo; Shi, Chuhan; Yin, Ming; Ma, Xiaojuan | J23: 2023 | K23: Business | L23: Proceedings of the 2023 CHI Conference on Human Factors in Computing Systems | M23: Between-Subjects | N23: Independent Samples | O23: Determine if person's income exceeds $50,000 | P23: Customer Segmentation | Q23: Multiple | R23: Yes | S23: No | T23: No | U23: Yes | V23: No | W23: No | X23: Binary | Y23: Binary | Z23: Decide | AA23: Shallow | AB23: Categoric, Numeric | AC23: Numeric | AD23: Rule-Based | AE23: Human | AF23: No | AG23: HAI = AI Confidence | AH23: No | AI23: Yes | AK23: Accuracy | AL23: Accuracy | AM23: Up | AN23: 293 | AO23: 59 | AP23: 59 | AQ23: Crowdworkers | AR23: Crowdworkers | AS23: Prolific | AT23: No | AU23: Yes | AV23: 0.721 | AW23: 0.7 | AX23: 0.72 | AY23: 0.721 | AZ23: 0.7 | BA23: 0.72 | BB23: Human | BC23: 0.721 | BD23: 0.7 | BE23: 0 | BF23: 0.113 | BG23: 0 | BH23: 0.099 | BI23: 0.113 | BJ23: 0 | BK23: No | BL23: HAI = AI
A24: Ma_2023 | B24: 14 | C24: 1 | D24: 2 | E24: 1 | F24: 14.1 | G24: 14.1.2.1 | H24: Who Should I Trust: AI or Myself? Leveraging Human and AI Correctness Likelihood to Promote Appropriate Trust in AI-Assisted Decision-Making | I24: Ma, Shuai; Lei, Ying; Wang, Xinru; Zheng, Chengbo; Shi, Chuhan; Yin, Ming; Ma, Xiaojuan | J24: 2023 | K24: Business | L24: Proceedings of the 2023 CHI Conference on Human Factors in Computing Systems | M24: Between-Subjects | N24: Independent Samples | O24: Determine if person's income exceeds $50,000 | P24: Customer Segmentation | Q24: Multiple | R24: Yes | S24: No | T24: No | U24: Yes | V24: No | W24: No | X24: Binary | Y24: Binary | Z24: Decide | AA24: Shallow | AB24: Categoric, Numeric | AC24: Numeric | AD24: Rule-Based | AE24: Human | AF24: No | AG24: HAI = Direct Display | AH24: No | AI24: Yes | AK24: Accuracy | AL24: Accuracy | AM24: Up | AN24: 293 | AO24: 59 | AP24: 59 | AQ24: Crowdworkers | AR24: Crowdworkers | AS24: Prolific | AT24: No | AU24: Yes | AV24: 0.721 | AW24: 0.7 | AX24: 0.758 | AY24: 0.721 | AZ24: 0.7 | BA24: 0.758 | BB24: Human | BC24: 0.721 | BD24: 0.7 | BE24: 1 | BF24: 0.113 | BG24: 0 | BH24: 0.078 | BI24: 0.113 | BJ24: 0 | BK24: No | BL24: HAI = AI + BD
A25: Ma_2023 | B25: 14 | C25: 1 | D25: 3 | E25: 1 | F25: 14.1 | G25: 14.1.3.1 | H25: Who Should I Trust: AI or Myself? Leveraging Human and AI Correctness Likelihood to Promote Appropriate Trust in AI-Assisted Decision-Making | I25: Ma, Shuai; Lei, Ying; Wang, Xinru; Zheng, Chengbo; Shi, Chuhan; Yin, Ming; Ma, Xiaojuan | J25: 2023 | K25: Business | L25: Proceedings of the 2023 CHI Conference on Human Factors in Computing Systems | M25: Between-Subjects | N25: Independent Samples | O25: Determine if person's income exceeds $50,000 | P25: Customer Segmentation | Q25: Multiple | R25: Yes | S25: No | T25: No | U25: Yes | V25: No | W25: No | X25: Binary | Y25: Binary | Z25: Decide | AA25: Shallow | AB25: Categoric, Numeric | AC25: Numeric | AD25: Rule-Based | AE25: Human | AF25: No | AG25: HAI = Adaptive Workflow | AH25: No | AI25: Yes | AK25: Accuracy | AL25: Accuracy | AM25: Up | AN25: 293 | AO25: 59 | AP25: 56 | AQ25: Crowdworkers | AR25: Crowdworkers | AS25: Prolific | AT25: No | AU25: Yes | AV25: 0.721 | AW25: 0.7 | AX25: 0.767 | AY25: 0.721 | AZ25: 0.7 | BA25: 0.767 | BB25: Human | BC25: 0.721 | BD25: 0.7 | BE25: 1 | BF25: 0.113 | BG25: 0 | BH25: 0.085 | BI25: 0.113 | BJ25: 0 | BK25: No | BL25: HAI = AI
A26: Ma_2023 | B26: 14 | C26: 1 | D26: 4 | E26: 1 | F26: 14.1 | G26: 14.1.4.1 | H26: Who Should I Trust: AI or Myself? Leveraging Human and AI Correctness Likelihood to Promote Appropriate Trust in AI-Assisted Decision-Making | I26: Ma, Shuai; Lei, Ying; Wang, Xinru; Zheng, Chengbo; Shi, Chuhan; Yin, Ming; Ma, Xiaojuan | J26: 2023 | K26: Business | L26: Proceedings of the 2023 CHI Conference on Human Factors in Computing Systems | M26: Between-Subjects | N26: Independent Samples | O26: Determine if person's income exceeds $50,000 | P26: Customer Segmentation | Q26: Multiple | R26: Yes | S26: No | T26: No | U26: Yes | V26: No | W26: No | X26: Binary | Y26: Binary | Z26: Decide | AA26: Shallow | AB26: Categoric, Numeric | AC26: Numeric | AD26: Rule-Based | AE26: Human | AF26: No | AG26: HAI = Adaptive Recommendation | AH26: Yes | AI26: Yes | AJ26: Image, Numeric | AK26: Accuracy | AL26: Accuracy | AM26: Up | AN26: 293 | AO26: 59 | AP26: 56 | AQ26: Crowdworkers | AR26: Crowdworkers | AS26: Prolific | AT26: No | AU26: Yes | AV26: 0.721 | AW26: 0.7 | AX26: 0.754 | AY26: 0.721 | AZ26: 0.7 | BA26: 0.754 | BB26: Human | BC26: 0.721 | BD26: 0.7 | BE26: 1 | BF26: 0.113 | BG26: 0 | BH26: 0.072 | BI26: 0.113 | BJ26: 0 | BK26: No | BL26: HAI = AI + BD
A27: Lehmann_2022 | B27: 20 | C27: 1 | D27: 1 | E27: 1 | F27: 20.1 | G27: 20.1.1.1 | H27: The risk of algorithm transparency: How algorithm complexity drives the effects on the use of advice | I27: Lehmann, Cedric A.; Haubitz, Christiane B.; Fuegener, Andreas; Thonemann, Ulrich W. | J27: 2022 | K27: Business | L27: Production and Operations Management | M27: Mixed, Within-Subjects | N27: Dependent Samples | O27: Forecast demand | P27: =VLOOKUP(O27,Sheet3!$A$1:$B$22,2,0) -> Demand Forecasting | Q27: Numeric | R27: No | S27: No | T27: No | U27: Yes | V27: No | W27: No | X27: Numeric | Y27: Numeric | Z27: Decide | AA27: Shallow | AB27: Numeric | AC27: Continuous | AD27: Rule-Based | AE27: Human | AF27: No | AG27: HAI = Nontransparent | AH27: No | AI27: No | AK27: MAE | AL27: Error | AM27: Down | AN27: 509 | AO27: 171 | AP27: 171 | AQ27: Crowdworkers | AR27: Crowdworkers | AS27: MTurk | AT27: No | AU27: Yes | AV27: 179.54 | AW27: 66.2 | AX27: 111.24 | AY27: -179.54 | AZ27: -66.2 | BA27: -111.24 | BB27: AI | BC27: -66.2 | BD27: -179.54 | BE27: 0 | BF27: 47.93 | BG27: 0 | BH27: 42.24 | BI27: 0 | BJ27: 47.93 | BK27: No | BL27: H = TagLab Manual; HAI = TagLabEdit
A28: Lehmann_2022 | B28: 20 | C28: 1 | D28: 2 | E28: 1 | F28: 20.1 | G28: 20.1.2.1 | H28: The risk of algorithm transparency: How algorithm complexity drives the effects on the use of advice | I28: Lehmann, Cedric A.; Haubitz, Christiane B.; Fuegener, Andreas; Thonemann, Ulrich W. | J28: 2022 | K28: Business | L28: Production and Operations Management | M28: Mixed, Within-Subjects | N28: Dependent Samples | O28: Forecast demand | P28: =VLOOKUP(O28,Sheet3!$A$1:$B$22,2,0) -> Demand Forecasting | Q28: Numeric | R28: No | S28: No | T28: No | U28: Yes | V28: No | W28: No | X28: Numeric | Y28: Numeric | Z28: Decide | AA28: Shallow | AB28: Numeric | AC28: Continuous | AD28: Rule-Based | AE28: Human | AF28: No | AG28: HAI = Transparent-simple | AH28: Yes | AI28: No | AJ28: Numeric, Text | AK28: MAE | AL28: Error | AM28: Down | AN28: 509 | AO28: 171 | AP28: 171 | AQ28: Crowdworkers | AR28: Crowdworkers | AS28: MTurk | AT28: No | AU28: Yes | AV28: 184.04 | AW28: 66.2 | AX28: 135 | AY28: -184.04 | AZ28: -66.2 | BA28: -135 | BB28: AI | BC28: -66.2 | BD28: -184.04 | BE28: 0 | BF28: 47.29 | BG28: 0 | BH28: 55.45 | BI28: 0 | BJ28: 47.29 | BK28: No | BL28: H = TagLab Manual; HAI = TagLabAssisted
A29: Lehmann_2022 | B29: 20 | C29: 1 | D29: 3 | E29: 1 | F29: 20.1 | G29: 20.1.3.1 | H29: The risk of algorithm transparency: How algorithm complexity drives the effects on the use of advice | I29: Lehmann, Cedric A.; Haubitz, Christiane B.; Fuegener, Andreas; Thonemann, Ulrich W. | J29: 2022 | K29: Business | L29: Production and Operations Management | M29: Mixed, Within-Subjects | N29: Dependent Samples | O29: Forecast demand | P29: =VLOOKUP(O29,Sheet3!$A$1:$B$22,2,0) -> Demand Forecasting | Q29: Numeric | R29: No | S29: No | T29: No | U29: Yes | V29: No | W29: No | X29: Numeric | Y29: Numeric | Z29: Decide | AA29: Shallow | AB29: Numeric | AC29: Continuous | AD29: Rule-Based | AE29: Human | AF29: No | AG29: HAI = Transparent | AH29: Yes | AI29: No | AJ29: Image, Numeric, Text | AK29: MAE | AL29: Error | AM29: Down | AN29: 509 | AO29: 167 | AP29: 167 | AQ29: Crowdworkers | AR29: Crowdworkers | AS29: MTurk | AT29: No | AU29: Yes | AV29: 181.81 | AW29: 66.2 | AX29: 106.79 | AY29: -181.81 | AZ29: -66.2 | BA29: -106.79 | BB29: AI | BC29: -66.2 | BD29: -181.81 | BE29: 0 | BF29: 43.61 | BG29: 0 | BH29: 42.9 | BI29: 0 | BJ29: 43.61 | BK29: No | BL29: H = TagLab Manual; HAI = TagLabEdit
A30: Skirzynski_2021 | B30: 27 | C30: 1 | D30: 1 | E30: 1 | F30: 27.1 | G30: 27.1.1.1 | H30: Automatic discovery of interpretable planning strategies | I30: Skirzynski, J; Becker, F; Lieder, F | J30: 2021 | K30: Business | L30: Machine Learning | M30: Between-Subjects | N30: Independent Samples | O30: Plan a route | P30: =VLOOKUP(O30,Sheet3!$A$1:$B$22,2,0) -> Demand Forecasting | Q30: Numeric | R30: No | S30: No | T30: No | U30: Yes | V30: No | W30: No | X30: Categoric | Y30: Categoric | Z30: Decide | AA30: Shallow | AB30: Numeric | AC30: Categorical | AD30: Rule-Based | AE30: Human | AF30: No | AG30: Increasing Variance | AH30: Yes | AI30: No | AJ30: Image, Text | AK30: Expected Score | AL30: Score | AM30: Up | AN30: 236 | AO30: 78 | AP30: 79 | AQ30: Crowdworkers | AR30: Crowdworkers | AS30: MTurk | AT30: No | AU30: Yes | AV30: 28.41 | AW30: 39.17 | AX30: 34.47 | AY30: 28.41 | AZ30: 39.17 | BA30: 34.47 | BB30: AI | BC30: 39.17 | BD30: 28.41 | BE30: 0 | BF30: 13.33 | BG30: 0 | BH30: 11.85 | BI30: 0 | BJ30: 13.33 | BK30: No | BL30: AI-FHD(Higher)
A31: Skirzynski_2021 | B31: 27 | C31: 2 | D31: 1 | E31: 1 | F31: 27.2 | G31: 27.2.1.1 | H31: Automatic discovery of interpretable planning strategies | I31: Skirzynski, J; Becker, F; Lieder, F | J31: 2021 | K31: Business | L31: Machine Learning | M31: Between-Subjects | N31: Independent Samples | O31: Plan a route | P31: =VLOOKUP(O31,Sheet3!$A$1:$B$22,2,0) -> Demand Forecasting | Q31: Numeric | R31: No | S31: No | T31: No | U31: Yes | V31: No | W31: No | X31: Categoric | Y31: Categoric | Z31: Decide | AA31: Shallow | AB31: Numeric | AC31: Categorical | AD31: Rule-Based | AE31: Human | AF31: No | AG31: Decreasing Variance | AH31: Yes | AI31: No | AJ31: Image, Text | AK31: Expected Score | AL31: Score | AM31: Up | AN31: 222 | AO31: 70 | AP31: 76 | AQ31: Crowdworkers | AR31: Crowdworkers | AS31: MTurk | AT31: No | AU31: Yes | AV31: 22.75 | AW31: 28.47 | AX31: 24.02 | AY31: 22.75 | AZ31: 28.47 | BA31: 24.02 | BB31: AI | BC31: 28.47 | BD31: 22.75 | BE31: 0 | BF31: 8.18 | BG31: 0 | BH31: 7.38 | BI31: 0 | BJ31: 8.18 | BK31: No | BL31: AI-XAI-FHD(Lower)
A32: Skirzynski_2021 | B32: 27 | C32: 3 | D32: 1 | E32: 1 | F32: 27.3 | G32: 27.3.1.1 | H32: Automatic discovery of interpretable planning strategies | I32: Skirzynski, J; Becker, F; Lieder, F | J32: 2021 | K32: Business | L32: Machine Learning | M32: Between-Subjects | N32: Independent Samples | O32: Plan a route | P32: =VLOOKUP(O32,Sheet3!$A$1:$B$22,2,0) -> Demand Forecasting | Q32: Numeric | R32: No | S32: No | T32: No | U32: Yes | V32: No | W32: No | X32: Categoric | Y32: Categoric | Z32: Decide | AA32: Shallow | AB32: Numeric | AC32: Categorical | AD32: Rule-Based | AE32: Human | AF32: No | AG32: Constant Variance | AH32: Yes | AI32: No | AJ32: Image, Text | AK32: Expected Score | AL32: Score | AM32: Up | AN32: 178 | AO32: 60 | AP32: 59 | AQ32: Crowdworkers | AR32: Crowdworkers | AS32: MTurk | AT32: No | AU32: Yes | AV32: 4.17 | AW32: 7.03 | AX32: 5.95 | AY32: 4.17 | AZ32: 7.03 | BA32: 5.95 | BB32: AI | BC32: 7.03 | BD32: 4.17 | BE32: 0 | BF32: 2.63 | BG32: 0 | BH32: 2.75 | BI32: 0 | BJ32: 2.63 | BK32: No | BL32: AI-XAI-FHD(Higher)
A33: Hemmer_2022 | B33: 68 | C33: 1 | D33: 2 | E33: 1 | F33: 68.1 | G33: 68.1.2.1 | H33: On the effect of information asymmetry in human-AI teams | I33: Hemmer, Patrick; Schemmer, Max; KÃ¼hl, Niklas; VÃ¶ssing, Michael; Satzger, Gerhard | J33: 2022 | K33: Business | L33: CHI Conference on Human Factors in Computing Systems (CHI '22), Workshop on Human-Centered Explainable AI (HCXAI) | M33: Between-Subjects | N33: Independent Samples | O33: Predict housing prices | P33: =VLOOKUP(O33,Sheet3!$A$1:$B$22,2,0) -> Demand Forecasting | Q33: Multiple | R33: Yes | S33: No | T33: No | U33: Yes | V33: No | W33: No | X33: Numeric | Y33: Numeric | Z33: Decide | AA33: Shallow | AB33: Categoric, Numeric | AC33: Continuous | AD33: Rule-Based | AE33: Human | AF33: No | AG33: UHCI | AH33: No | AI33: Yes | AK33: MAE | AL33: Error | AM33: Down | AN33: 154 | AO33: 48 | AP33: 48 | AQ33: Crowdworkers | AR33: Crowdworkers | AS33: Prolific | AT33: No | AU33: Yes | AV33: 200510 | AW33: 163080 | AX33: 148009 | AY33: -200510 | AZ33: -163080 | BA33: -148009 | BB33: AI | BC33: -163080 | BD33: -200510 | BE33: 1 | BF33: 45348 | BG33: 0 | BH33: 22079 | BI33: 0 | BJ33: 45348 | BK33: No | BL33: Concurrent, AI, HAI = B, Noise = 125
A34: Chen_2023 | B34: 69 | C34: 1 | D34: 1 | E34: 1 | F34: 69.1 | G34: 69.1.1.1 | H34: Understanding the role of human intuition on reliance in human-AI decision-making with explanations | I34: Chen, Valerie; Liao, Q. Vera; Vaughan, Jennifer Wortman; Bansal, Gagan | J34: 2023 | K34: Business | L34: CSCW 2023 | M34: Within-Subjects | N34: Dependent Samples | O34: Predict housing prices | P34: =VLOOKUP(O34,Sheet3!$A$1:$B$22,2,0) -> Demand Forecasting | Q34: Multiple | R34: Yes | S34: No | T34: No | U34: Yes | V34: No | W34: No | X34: Binary | Y34: Binary | Z34: Decide | AA34: Shallow | AB34: Categoric, Numeric | AC34: Binary | AD34: Rule-Based | AE34: Human | AF34: No | AG34: HAI = Feature-Based | AH34: Yes | AI34: No | AJ34: Image, Numeric | AK34: Accuracy | AL34: Accuracy | AM34: Up | AN34: 13 | AO34: 13 | AP34: 13 | AQ34: Volunteers | AR34: Volunteers | AS34: Email, Twitter | AT34: No | AU34: No | AV34: 0.611 | AW34: 0.625 | AX34: 0.606 | AY34: 0.611 | AZ34: 0.625 | BA34: 0.606 | BB34: AI | BC34: 0.625 | BD34: 0.611 | BE34: 0 | BF34: 0.1046 | BG34: 0 | BH34: 0.1514 | BI34: 0 | BJ34: 0.1046 | BK34: No | BL34: Concurrent, AI, HAI = B, Noise = 140
A35: Chen_2023 | B35: 69 | C35: 1 | D35: 2 | E35: 1 | F35: 69.1 | G35: 69.1.2.1 | H35: Understanding the role of human intuition on reliance in human-AI decision-making with explanations | I35: Chen, Valerie; Liao, Q. Vera; Vaughan, Jennifer Wortman; Bansal, Gagan | J35: 2023 | K35: Business | L35: CSCW 2023 | M35: Within-Subjects | N35: Dependent Samples | O35: Predict housing prices | P35: =VLOOKUP(O35,Sheet3!$A$1:$B$22,2,0) -> Demand Forecasting | Q35: Multiple | R35: Yes | S35: No | T35: No | U35: Yes | V35: No | W35: No | X35: Binary | Y35: Binary | Z35: Decide | AA35: Shallow | AB35: Categoric, Numeric | AC35: Binary | AD35: Rule-Based | AE35: Human | AF35: No | AG35: HAI = Example-Based | AH35: Yes | AI35: No | AJ35: Image, Numeric, Text | AK35: Accuracy | AL35: Accuracy | AM35: Up | AN35: 13 | AO35: 13 | AP35: 13 | AQ35: Volunteers | AR35: Volunteers | AS35: Email, Twitter | AT35: No | AU35: No | AV35: 0.611 | AW35: 0.625 | AX35: 0.711 | AY35: 0.611 | AZ35: 0.625 | BA35: 0.711 | BB35: AI | BC35: 0.625 | BD35: 0.611 | BE35: 1 | BF35: 0.1046 | BG35: 0 | BH35: 0.1046 | BI35: 0 | BJ35: 0.1046 | BK35: No | BL35: Concurrent, AI, HAI = B, Noise = 155
A36: Chen_2023 | B36: 69 | C36: 2 | D36: 1 | E36: 1 | F36: 69.2 | G36: 69.2.1.1 | H36: Understanding the role of human intuition on reliance in human-AI decision-making with explanations | I36: Chen, Valerie; Liao, Q. Vera; Vaughan, Jennifer Wortman; Bansal, Gagan | J36: 2023 | K36: Business | L36: CSCW 2023 | M36: Within-Subjects | N36: Dependent Samples | O36: Predict housing prices | P36: =VLOOKUP(O36,Sheet3!$A$1:$B$22,2,0) -> Demand Forecasting | Q36: Multiple | R36: Yes | S36: No | T36: No | U36: Yes | V36: No | W36: No | X36: Categoric | Y36: Categoric | Z36: Decide | AA36: Shallow | AB36: Categoric, Numeric | AC36: Categorical | AD36: Rule-Based | AE36: Human | AF36: No | AG36: HAI = Feature-Based | AH36: Yes | AI36: No | AJ36: Image, Numeric | AK36: Accuracy | AL36: Accuracy | AM36: Up | AN36: 13 | AO36: 13 | AP36: 13 | AQ36: Volunteers | AR36: Volunteers | AS36: Email, Twitter | AT36: No | AU36: No | AV36: 0.6 | AW36: 0.625 | AX36: 0.644 | AY36: 0.6 | AZ36: 0.625 | BA36: 0.644 | BB36: AI | BC36: 0.625 | BD36: 0.6 | BE36: 1 | BF36: 0.1586 | BG36: 0 | BH36: 0.155 | BI36: 0 | BJ36: 0.1586 | BK36: No | BL36: Concurrent, AI, HAI = B, Noise = 170
A37: Chen_2023 | B37: 69 | C37: 2 | D37: 2 | E37: 1 | F37: 69.2 | G37: 69.2.2.1 | H37: Understanding the role of human intuition on reliance in human-AI decision-making with explanations | I37: Chen, Valerie; Liao, Q. Vera; Vaughan, Jennifer Wortman; Bansal, Gagan | J37: 2023 | K37: Business | L37: CSCW 2023 | M37: Within-Subjects | N37: Dependent Samples | O37: Predict a person's profession | P37: Customer Segmentation | Q37: Multiple | R37: Yes | S37: No | T37: No | U37: Yes | V37: No | W37: No | X37: Categoric | Y37: Categoric | Z37: Decide | AA37: Shallow | AB37: Categoric, Numeric | AC37: Categorical | AD37: Rule-Based | AE37: Human | AF37: No | AG37: HAI = Example-Based | AH37: Yes | AI37: No | AJ37: Image, Numeric, Text | AK37: Accuracy | AL37: Accuracy | AM37: Up | AN37: 13 | AO37: 13 | AP37: 13 | AQ37: Volunteers | AR37: Volunteers | AS37: Email, Twitter | AT37: No | AU37: No | AV37: 0.6 | AW37: 0.625 | AX37: 0.712 | AY37: 0.6 | AZ37: 0.625 | BA37: 0.712 | BB37: AI | BC37: 0.625 | BD37: 0.6 | BE37: 1 | BF37: 0.1586 | BG37: 0 | BH37: 0.1659 | BI37: 0 | BJ37: 0.1586 | BK37: No | BL37: Concurrent, AI, HAI = C, Noise = 0
A38: Elder_2022 | B38: 72 | C38: 1 | D38: 1 | E38: 1 | F38: 72.1 | G38: 72.1.1.1 | H38: Knowing when to pass: The effect of AI reliability in risky decision contexts | I38: Elder, Hannah; Canfield, Casey; Shank, Daniel B.; Rieger, Tobias; Hines, Casey | J38: 2022 | K38: Business | L38: Human Factors | M38: Between-Subjects | N38: Independent Samples | O38: Predict basketball games | P38: =VLOOKUP(O38,Sheet3!$A$1:$B$22,2,0) -> Demand Forecasting | Q38: Numeric | R38: No | S38: No | T38: No | U38: Yes | V38: No | W38: No | X38: Binary | Y38: Binary | Z38: Decide | AA38: Wizard of Oz | AB38: Numeric | AC38: Binary | AD38: Simulated-AI | AE38: Human | AF38: No | AG38: Low Acc | AH38: No | AI38: No | AK38: Accuracy | AL38: Accuracy | AM38: Up | AN38: 245 | AO38: 81 | AP38: 82 | AQ38: Crowdworkers | AR38: Crowdworkers | AS38: Prolific | AT38: No | AU38: Yes | AV38: 0.52 | AW38: 0.6 | AX38: 0.57 | AY38: 0.52 | AZ38: 0.6 | BA38: 0.57 | BB38: AI | BC38: 0.6 | BD38: 0.52 | BE38: 0 | BF38: 0.09 | BG38: 0 | BH38: 0.1 | BI38: 0 | BJ38: 0.09 | BK38: No
A39: Elder_2022 | B39: 72 | C39: 1 | D39: 1 | E39: 2 | F39: 72.1 | G39: 72.1.1.2 | H39: Knowing when to pass: The effect of AI reliability in risky decision contexts | I39: Elder, Hannah; Canfield, Casey; Shank, Daniel B.; Rieger, Tobias; Hines, Casey | J39: 2022 | K39: Business | L39: Human Factors | M39: Between-Subjects | N39: Independent Samples | O39: Predict basketball games | P39: =VLOOKUP(O39,Sheet3!$A$1:$B$22,2,0) -> Demand Forecasting | Q39: Numeric | R39: No | S39: No | T39: No | U39: Yes | V39: No | W39: No | X39: Binary | Y39: Binary | Z39: Decide | AA39: Wizard of Oz | AB39: Numeric | AC39: Binary | AD39: Simulated-AI | AE39: Human | AF39: No | AG39: Low Acc | AH39: No | AI39: No | AK39: Sensitivity (d') | AL39: Error Rate | AM39: Up | AN39: 245 | AO39: 81 | AP39: 82 | AQ39: Crowdworkers | AR39: Crowdworkers | AS39: Prolific | AT39: No | AU39: Yes | AV39: -0.08 | AW39: 0.76 | AX39: 0.22 | AY39: -0.08 | AZ39: 0.76 | BA39: 0.22 | BB39: AI | BC39: 0.76 | BD39: -0.08 | BE39: 0 | BF39: 0.5 | BG39: 0 | BH39: 0.59 | BI39: 0 | BJ39: 0.5 | BK39: No
A40: Elder_2022 | B40: 72 | C40: 1 | D40: 1 | E40: 3 | F40: 72.1 | G40: 72.1.1.3 | H40: Knowing when to pass: The effect of AI reliability in risky decision contexts | I40: Elder, Hannah; Canfield, Casey; Shank, Daniel B.; Rieger, Tobias; Hines, Casey | J40: 2022 | K40: Business | L40: Human Factors | M40: Between-Subjects | N40: Independent Samples | O40: Predict basketball games | P40: =VLOOKUP(O40,Sheet3!$A$1:$B$22,2,0) -> Demand Forecasting | Q40: Numeric | R40: No | S40: No | T40: No | U40: Yes | V40: No | W40: No | X40: Binary | Y40: Binary | Z40: Decide | AA40: Wizard of Oz | AB40: Numeric | AC40: Binary | AD40: Simulated-AI | AE40: Human | AF40: No | AG40: Low Acc | AH40: No | AI40: No | AK40: Response Bias | AL40: Error Rate | AM40: Down | AN40: 245 | AO40: 81 | AP40: 82 | AQ40: Crowdworkers | AR40: Crowdworkers | AS40: Prolific | AT40: No | AU40: Yes | AV40: 0.33 | AW40: 0.9 | AX40: 0.41 | AY40: 0.33 | AZ40: 0.9 | BA40: 0.41 | BB40: AI | BC40: 0.9 | BD40: 0.33 | BE40: 0 | BF40: 0.44 | BG40: 0 | BH40: 0.49 | BI40: 0 | BJ40: 0.44 | BK40: No
A41: Elder_2022 | B41: 72 | C41: 1 | D41: 2 | E41: 1 | F41: 72.1 | G41: 72.1.2.1 | H41: Knowing when to pass: The effect of AI reliability in risky decision contexts | I41: Elder, Hannah; Canfield, Casey; Shank, Daniel B.; Rieger, Tobias; Hines, Casey | J41: 2022 | K41: Business | L41: Human Factors | M41: Between-Subjects | N41: Independent Samples | O41: Predict basketball games | P41: =VLOOKUP(O41,Sheet3!$A$1:$B$22,2,0) -> Demand Forecasting | Q41: Numeric | R41: No | S41: No | T41: No | U41: Yes | V41: No | W41: No | X41: Binary | Y41: Binary | Z41: Decide | AA41: Wizard of Oz | AB41: Numeric | AC41: Binary | AD41: Simulated-AI | AE41: Human | AF41: No | AG41: High Acc | AH41: No | AI41: No | AK41: Accuracy | AL41: Accuracy | AM41: Up | AN41: 245 | AO41: 81 | AP41: 82 | AQ41: Crowdworkers | AR41: Crowdworkers | AS41: Prolific | AT41: No | AU41: Yes | AV41: 0.52 | AW41: 0.85 | AX41: 0.68 | AY41: 0.52 | AZ41: 0.85 | BA41: 0.68 | BB41: AI | BC41: 0.85 | BD41: 0.52 | BE41: 0 | BF41: 0.09 | BG41: 0 | BH41: 0.12 | BI41: 0 | BJ41: 0.09 | BK41: No
A42: Elder_2022 | B42: 72 | C42: 1 | D42: 2 | E42: 2 | F42: 72.1 | G42: 72.1.2.2 | H42: Knowing when to pass: The effect of AI reliability in risky decision contexts | I42: Elder, Hannah; Canfield, Casey; Shank, Daniel B.; Rieger, Tobias; Hines, Casey | J42: 2022 | K42: Business | L42: Human Factors | M42: Between-Subjects | N42: Independent Samples | O42: Predict basketball games | P42: =VLOOKUP(O42,Sheet3!$A$1:$B$22,2,0) -> Demand Forecasting | Q42: Numeric | R42: No | S42: No | T42: No | U42: Yes | V42: No | W42: No | X42: Binary | Y42: Binary | Z42: Decide | AA42: Wizard of Oz | AB42: Numeric | AC42: Binary | AD42: Simulated-AI | AE42: Human | AF42: No | AG42: High Acc | AH42: No | AI42: No | AK42: Sensitivity (d') | AL42: Error Rate | AM42: Up | AN42: 245 | AO42: 81 | AP42: 82 | AQ42: Crowdworkers | AR42: Crowdworkers | AS42: Prolific | AT42: No | AU42: Yes | AV42: -0.08 | AW42: 2.12 | AX42: 0.83 | AY42: -0.08 | AZ42: 2.12 | BA42: 0.83 | BB42: AI | BC42: 2.12 | BD42: -0.08 | BE42: 0 | BF42: 0.5 | BG42: 0 | BH42: 0.68 | BI42: 0 | BJ42: 0.5 | BK42: No
A43: Elder_2022 | B43: 72 | C43: 1 | D43: 2 | E43: 3 | F43: 72.1 | G43: 72.1.2.3 | H43: Knowing when to pass: The effect of AI reliability in risky decision contexts | I43: Elder, Hannah; Canfield, Casey; Shank, Daniel B.; Rieger, Tobias; Hines, Casey | J43: 2022 | K43: Business | L43: Human Factors | M43: Between-Subjects | N43: Independent Samples | O43: Predict basketball games | P43: =VLOOKUP(O43,Sheet3!$A$1:$B$22,2,0) -> Demand Forecasting | Q43: Numeric | R43: No | S43: No | T43: No | U43: Yes | V43: No | W43: No | X43: Binary | Y43: Binary | Z43: Decide | AA43: Wizard of Oz | AB43: Numeric | AC43: Binary | AD43: Simulated-AI | AE43: Human | AF43: No | AG43: High Acc | AH43: No | AI43: No | AK43: Response Bias | AL43: Error Rate | AM43: Down | AN43: 245 | AO43: 81 | AP43: 82 | AQ43: Crowdworkers | AR43: Crowdworkers | AS43: Prolific | AT43: No | AU43: Yes | AV43: 0.33 | AW43: 0.22 | AX43: 0.2 | AY43: 0.33 | AZ43: 0.22 | BA43: 0.2 | BB43: Human | BC43: 0.33 | BD43: 0.22 | BE43: 0 | BF43: 0.44 | BG43: 0 | BH43: 0.41 | BI43: 0.44 | BJ43: 0 | BK43: No
A44: Bondi_2022 | B44: 74 | C44: 1 | D44: 1 | E44: 1 | F44: 74.1 | G44: 74.1.1.1 | H44: Role of human-AI interaction in selective prediction | I44: Bondi, Elizabeth; Koster, Raphael; Sheahan, Hannah; Chadwick, Martin; Bachrach, Yoram; Cemgil, Taylan; Paquet, Ulrich; Dvijotham, Krishnamurthy | J44: 2022 | K44: Business | L44: Proceedings of the AAAI Conference on Artificial Intelligence | M44: Within-Subjects | N44: Dependent Samples | O44: Detect animal in image | P44: Social Listening | Q44: Image | R44: No | S44: No | T44: Yes | U44: No | V44: No | W44: No | X44: Binary | Y44: Binary | Z44: Decide | AA44: Deep | AB44: Image | AC44: Binary | AD44: Deep | AE44: Human | AF44: No | AG44: H = NM, HAI = DO | AH44: No | AI44: No | AK44: Accuracy | AL44: Accuracy | AM44: Up | AN44: 198 | AO44: 198 | AP44: 198 | AQ44: Crowdworkers | AR44: Crowdworkers | AS44: Prolific | AT44: No | AU44: Yes | AV44: 0.5848 | AW44: 0.5 | AX44: 0.6197 | AY44: 0.5848 | AZ44: 0.5 | BA44: 0.6197 | BB44: Human | BC44: 0.5848 | BD44: 0.5 | BE44: 1 | BF44: 0.1127 | BG44: 0 | BH44: 0.1088 | BI44: 0.11269305 | BJ44: 0 | BK44: No
A45: Bondi_2022 | B45: 74 | C45: 1 | D45: 2 | E45: 1 | F45: 74.1 | G45: 74.1.2.1 | H45: Role of human-AI interaction in selective prediction | I45: Bondi, Elizabeth; Koster, Raphael; Sheahan, Hannah; Chadwick, Martin; Bachrach, Yoram; Cemgil, Taylan; Paquet, Ulrich; Dvijotham, Krishnamurthy | J45: 2022 | K45: Business | L45: Proceedings of the AAAI Conference on Artificial Intelligence | M45: Within-Subjects | N45: Dependent Samples | O45: Detect animal in image | P45: Social Listening | Q45: Image | R45: No | S45: No | T45: Yes | U45: No | V45: No | W45: No | X45: Binary | Y45: Binary | Z45: Decide | AA45: Deep | AB45: Image | AC45: Binary | AD45: Deep | AE45: Human | AF45: No | AG45: H = NM, HAI = PO | AH45: No | AI45: No | AK45: Accuracy | AL45: Accuracy | AM45: Up | AN45: 198 | AO45: 198 | AP45: 198 | AQ45: Crowdworkers | AR45: Crowdworkers | AS45: Prolific | AT45: No | AU45: Yes | AV45: 0.5848 | AW45: 0.5 | AX45: 0.5669 | AY45: 0.5848 | AZ45: 0.5 | BA45: 0.5669 | BB45: Human | BC45: 0.5848 | BD45: 0.5 | BE45: 0 | BF45: 0.1127 | BG45: 0 | BH45: 0.0878 | BI45: 0.11269305 | BJ45: 0 | BK45: No
A46: Bondi_2022 | B46: 74 | C46: 1 | D46: 3 | E46: 1 | F46: 74.1 | G46: 74.1.3.1 | H46: Role of human-AI interaction in selective prediction | I46: Bondi, Elizabeth; Koster, Raphael; Sheahan, Hannah; Chadwick, Martin; Bachrach, Yoram; Cemgil, Taylan; Paquet, Ulrich; Dvijotham, Krishnamurthy | J46: 2022 | K46: Business | L46: Proceedings of the AAAI Conference on Artificial Intelligence | M46: Within-Subjects | N46: Dependent Samples | O46: Detect animal in image | P46: Social Listening | Q46: Image | R46: No | S46: No | T46: Yes | U46: No | V46: No | W46: No | X46: Binary | Y46: Binary | Z46: Decide | AA46: Deep | AB46: Image | AC46: Binary | AD46: Deep | AE46: Human | AF46: No | AG46: H = NM, HAI = BM | AH46: No | AI46: No | AK46: Accuracy | AL46: Accuracy | AM46: Up | AN46: 198 | AO46: 198 | AP46: 198 | AQ46: Crowdworkers | AR46: Crowdworkers | AS46: Prolific | AT46: No | AU46: Yes | AV46: 0.5848 | AW46: 0.5 | AX46: 0.5899 | AY46: 0.5848 | AZ46: 0.5 | BA46: 0.5899 | BB46: Human | BC46: 0.5848 | BD46: 0.5 | BE46: 1 | BF46: 0.1127 | BG46: 0 | BH46: 0.1294 | BI46: 0.11269305 | BJ46: 0 | BK46: No
A47: Lu_Peng_2024 | B47: 84 | C47: 4 | D47: 1 | E47: 1 | F47: 4.1 | G47: Lu_Peng_2024_1 | H47: Human-AI Collaboration: Unraveling the Effects of User Proficiency and AI Agent Capability in Intelligent Decision Support Systems | I47: Lu Peng, Xiangbin Yan, Yunan Hu, Xin Luo | J47: 2024 | K47: Business | L47: Decision Support Systems | M47: Between-subjects | N47: Dependent Samples | O47: Decision-making accuracy in an AI-assisted decision support system | P47: =VLOOKUP(O47,Sheet3!$A$1:$B$22,2,0) -> Customer Service | Q47: Image | R47: No | S47: No | T47: No | U47: Yes | V47: Yes | W47: No | X47: Categoric | Y47: Categoric | Z47: Decide | AA47: Deep | AB47: Continuous | AC47: Continuous | AD47: Deep | AE47: Human | AF47: No | AG47: Human alone, AI alone, Human-AI collaboration | AH47: Yes | AI47: Yes | AJ47: Text-based decision rationale | AK47: Accuracy | AL47: Accuracy | AM47: Up | AN47: 4 | AO47: 320 | AP47: 320 | AQ47: Crowdworkers | AR47: Crowdworkers | AS47: Prolific | AT47: No | AU47: Yes | AV47: 0.542 | AW47: 0.8 | AX47: 0.668 | AY47: 0.542 | AZ47: 0.8 | BA47: 0.668 | BB47: AI | BC47: 0.8 | BD47: 0.542 | BE47: 0 | BF47: 0.19 | BG47: 0 | BH47: 0.13 | BI47: 0 | BJ47: 0.19 | BK47: Yes | BL47: Performance measured as accuracy in AI-assisted decision support tasks | BM47: Human-AI collaboration improved accuracy but did not exceed AI baseline
A48: Carton_2020 | B48: 43 | C48: 1 | D48: 1 | E48: 1 | F48: 43.1 | G48: 43.1.1.1 | H48: Feature-based explanations don't help people detect misclassifications of online toxicity | I48: Carton, Samuel; Mei, Qiaozhu; Resnick, Paul | J48: 2020 | K48: Communication | L48: Proceedings of the international AAAI conference on web and social media | M48: Between-Subjects | N48: Independent Samples | O48: Classify toxic comments | P48: =VLOOKUP(O48,Sheet3!$A$1:$B$22,2,0) -> Review Analysis | Q48: Text | R48: No | S48: No | T48: No | U48: No | V48: Yes | W48: No | X48: Categoric | Y48: Categoric | Z48: Decide | AA48: Deep | AB48: Text | AC48: Categorical | AD48: Deep | AE48: Human | AF48: No | AG48: HAI = Pred + no exp | AH48: No | AI48: No | AK48: Accuracy | AL48: Accuracy | AM48: Up | AN48: 480 | AO48: 80 | AP48: 80 | AQ48: Crowdworkers | AR48: Crowdworkers | AS48: MTurk | AT48: No | AU48: Yes | AV48: 0.544 | AW48: 0.375 | AX48: 0.525 | AY48: 0.544 | AZ48: 0.375 | BA48: 0.525 | BB48: Human | BC48: 0.544 | BD48: 0.375 | BE48: 0 | BF48: 0.115 | BG48: 0 | BH48: 0.1018 | BI48: 0.115 | BJ48: 0 | BK48: Yes | BL48: HAI = Pred + full exp
A49: Carton_2020 | B49: 43 | C49: 1 | D49: 1 | E49: 2 | F49: 43.1 | G49: 43.1.1.2 | H49: Feature-based explanations don't help people detect misclassifications of online toxicity | I49: Carton, Samuel; Mei, Qiaozhu; Resnick, Paul | J49: 2020 | K49: Communication | L49: Proceedings of the international AAAI conference on web and social media | M49: Between-Subjects | N49: Independent Samples | O49: Classify toxic comments | P49: =VLOOKUP(O49,Sheet3!$A$1:$B$22,2,0) -> Review Analysis | Q49: Text | R49: No | S49: No | T49: No | U49: No | V49: Yes | W49: No | X49: Categoric | Y49: Categoric | Z49: Decide | AA49: Deep | AB49: Text | AC49: Categorical | AD49: Deep | AE49: Human | AF49: No | AG49: HAI = Pred + no exp | AH49: No | AI49: No | AK49: FNR | AL49: Error Rate | AM49: Down | AN49: 480 | AO49: 80 | AP49: 80 | AQ49: Crowdworkers | AR49: Crowdworkers | AS49: MTurk | AT49: No | AU49: Yes | AV49: 0.276 | AW49: 0.396 | AX49: 0.315 | AY49: -0.276 | AZ49: -0.396 | BA49: -0.315 | BB49: Human | BC49: -0.276 | BD49: -0.396 | BE49: 0 | BF49: 0.122 | BG49: 0 | BH49: 0.1015 | BI49: 0.122 | BJ49: 0 | BK49: Yes | BL49: HAI = Pred + partial exp
A50: Carton_2020 | B50: 43 | C50: 1 | D50: 1 | E50: 3 | F50: 43.1 | G50: 43.1.1.3 | H50: Feature-based explanations don't help people detect misclassifications of online toxicity | I50: Carton, Samuel; Mei, Qiaozhu; Resnick, Paul | J50: 2020 | K50: Communication | L50: Proceedings of the international AAAI conference on web and social media | M50: Between-Subjects | N50: Independent Samples | O50: Classify toxic comments | P50: =VLOOKUP(O50,Sheet3!$A$1:$B$22,2,0) -> Review Analysis | Q50: Text | R50: No | S50: No | T50: No | U50: No | V50: Yes | W50: No | X50: Categoric | Y50: Categoric | Z50: Decide | AA50: Deep | AB50: Text | AC50: Categorical | AD50: Deep | AE50: Human | AF50: No | AG50: HAI = Pred + no exp | AH50: No | AI50: No | AK50: FPR | AL50: Error Rate | AM50: Down | AN50: 480 | AO50: 80 | AP50: 80 | AQ50: Crowdworkers | AR50: Crowdworkers | AS50: MTurk | AT50: No | AU50: Yes | AV50: 0.179 | AW50: 0.229 | AX50: 0.16 | AY50: -0.179 | AZ50: -0.229 | BA50: -0.16 | BB50: Human | BC50: -0.179 | BD50: -0.229 | BE50: 1 | BF50: 0.096 | BG50: 0 | BH50: 0.071 | BI50: 0.096 | BJ50: 0 | BK50: Yes | BL50: HAI = keyword exp
A51: Carton_2020 | B51: 43 | C51: 1 | D51: 2 | E51: 1 | F51: 43.1 | G51: 43.1.2.1 | H51: Feature-based explanations don't help people detect misclassifications of online toxicity | I51: Carton, Samuel; Mei, Qiaozhu; Resnick, Paul | J51: 2020 | K51: Communication | L51: Proceedings of the international AAAI conference on web and social media | M51: Between-Subjects | N51: Independent Samples | O51: Classify toxic comments | P51: =VLOOKUP(O51,Sheet3!$A$1:$B$22,2,0) -> Review Analysis | Q51: Text | R51: No | S51: No | T51: No | U51: No | V51: Yes | W51: No | X51: Categoric | Y51: Categoric | Z51: Decide | AA51: Deep | AB51: Text | AC51: Categorical | AD51: Deep | AE51: Human | AF51: No | AG51: HAI = Pred + full exp | AH51: Yes | AI51: No | AJ51: Image, Text | AK51: Accuracy | AL51: Accuracy | AM51: Up | AN51: 480 | AO51: 80 | AP51: 80 | AQ51: Crowdworkers | AR51: Crowdworkers | AS51: MTurk | AT51: No | AU51: Yes | AV51: 0.544 | AW51: 0.375 | AX51: 0.524 | AY51: 0.544 | AZ51: 0.375 | BA51: 0.524 | BB51: Human | BC51: 0.544 | BD51: 0.375 | BE51: 0 | BF51: 0.115 | BG51: 0 | BH51: 0.0931 | BI51: 0.115 | BJ51: 0 | BK51: Yes | BL51: HAI = No pred + full exp
A52: Carton_2020 | B52: 43 | C52: 1 | D52: 2 | E52: 2 | F52: 43.1 | G52: 43.1.2.2 | H52: Feature-based explanations don't help people detect misclassifications of online toxicity | I52: Carton, Samuel; Mei, Qiaozhu; Resnick, Paul | J52: 2020 | K52: Communication | L52: Proceedings of the international AAAI conference on web and social media | M52: Between-Subjects | N52: Independent Samples | O52: Classify toxic comments | P52: =VLOOKUP(O52,Sheet3!$A$1:$B$22,2,0) -> Review Analysis | Q52: Text | R52: No | S52: No | T52: No | U52: No | V52: Yes | W52: No | X52: Categoric | Y52: Categoric | Z52: Decide | AA52: Deep | AB52: Text | AC52: Categorical | AD52: Deep | AE52: Human | AF52: No | AG52: HAI = Pred + full exp | AH52: Yes | AI52: No | AJ52: Image, Text | AK52: FNR | AL52: Error Rate | AM52: Down | AN52: 480 | AO52: 80 | AP52: 80 | AQ52: Crowdworkers | AR52: Crowdworkers | AS52: MTurk | AT52: No | AU52: Yes | AV52: 0.276 | AW52: 0.396 | AX52: 0.337 | AY52: -0.276 | AZ52: -0.396 | BA52: -0.337 | BB52: Human | BC52: -0.276 | BD52: -0.396 | BE52: 0 | BF52: 0.122 | BG52: 0 | BH52: 0.1 | BI52: 0.122 | BJ52: 0 | BK52: Yes | BL52: H = traditional, AI = Non-Interactive RB1, HAI = Interactive RB 10
A53: Carton_2020 | B53: 43 | C53: 1 | D53: 2 | E53: 3 | F53: 43.1 | G53: 43.1.2.3 | H53: Feature-based explanations don't help people detect misclassifications of online toxicity | I53: Carton, Samuel; Mei, Qiaozhu; Resnick, Paul | J53: 2020 | K53: Communication | L53: Proceedings of the international AAAI conference on web and social media | M53: Between-Subjects | N53: Independent Samples | O53: Classify toxic comments | P53: =VLOOKUP(O53,Sheet3!$A$1:$B$22,2,0) -> Review Analysis | Q53: Text | R53: No | S53: No | T53: No | U53: No | V53: Yes | W53: No | X53: Categoric | Y53: Categoric | Z53: Decide | AA53: Deep | AB53: Text | AC53: Categorical | AD53: Deep | AE53: Human | AF53: No | AG53: HAI = Pred + full exp | AH53: Yes | AI53: No | AJ53: Image, Text | AK53: FPR | AL53: Error Rate | AM53: Down | AN53: 480 | AO53: 80 | AP53: 80 | AQ53: Crowdworkers | AR53: Crowdworkers | AS53: MTurk | AT53: No | AU53: Yes | AV53: 0.179 | AW53: 0.229 | AX53: 0.139 | AY53: -0.179 | AZ53: -0.229 | BA53: -0.139 | BB53: Human | BC53: -0.179 | BD53: -0.229 | BE53: 1 | BF53: 0.096 | BG53: 0 | BH53: 0.0958 | BI53: 0.096 | BJ53: 0 | BK53: Yes | BL53: H = traditional, AI = Non-Interactive HM1, HAI = Interactive HM 10
A54: Carton_2020 | B54: 43 | C54: 1 | D54: 3 | E54: 1 | F54: 43.1 | G54: 43.1.3.1 | H54: Feature-based explanations don't help people detect misclassifications of online toxicity | I54: Carton, Samuel; Mei, Qiaozhu; Resnick, Paul | J54: 2020 | K54: Communication | L54: Proceedings of the international AAAI conference on web and social media | M54: Between-Subjects | N54: Independent Samples | O54: Classify toxic comments | P54: =VLOOKUP(O54,Sheet3!$A$1:$B$22,2,0) -> Review Analysis | Q54: Text | R54: No | S54: No | T54: No | U54: No | V54: Yes | W54: No | X54: Categoric | Y54: Categoric | Z54: Decide | AA54: Deep | AB54: Text | AC54: Categorical | AD54: Deep | AE54: Human | AF54: No | AG54: HAI = Pred + partial exp | AH54: Yes | AI54: No | AJ54: Image, Text | AK54: Accuracy | AL54: Accuracy | AM54: Up | AN54: 480 | AO54: 80 | AP54: 80 | AQ54: Crowdworkers | AR54: Crowdworkers | AS54: MTurk | AT54: No | AU54: Yes | AV54: 0.544 | AW54: 0.375 | AX54: 0.526 | AY54: 0.544 | AZ54: 0.375 | BA54: 0.526 | BB54: Human | BC54: 0.544 | BD54: 0.375 | BE54: 0 | BF54: 0.115 | BG54: 0 | BH54: 0.1079 | BI54: 0.115 | BJ54: 0 | BK54: Yes | BL54: Image; HAI = grid
A55: Carton_2020 | B55: 43 | C55: 1 | D55: 3 | E55: 2 | F55: 43.1 | G55: 43.1.3.2 | H55: Feature-based explanations don't help people detect misclassifications of online toxicity | I55: Carton, Samuel; Mei, Qiaozhu; Resnick, Paul | J55: 2020 | K55: Communication | L55: Proceedings of the international AAAI conference on web and social media | M55: Between-Subjects | N55: Independent Samples | O55: Classify toxic comments | P55: =VLOOKUP(O55,Sheet3!$A$1:$B$22,2,0) -> Review Analysis | Q55: Text | R55: No | S55: No | T55: No | U55: No | V55: Yes | W55: No | X55: Categoric | Y55: Categoric | Z55: Decide | AA55: Deep | AB55: Text | AC55: Categorical | AD55: Deep | AE55: Human | AF55: No | AG55: HAI = Pred + partial exp | AH55: Yes | AI55: No | AJ55: Image, Text | AK55: FNR | AL55: Error Rate | AM55: Down | AN55: 480 | AO55: 80 | AP55: 80 | AQ55: Crowdworkers | AR55: Crowdworkers | AS55: MTurk | AT55: No | AU55: Yes | AV55: 0.276 | AW55: 0.396 | AX55: 0.357 | AY55: -0.276 | AZ55: -0.396 | BA55: -0.357 | BB55: Human | BC55: -0.276 | BD55: -0.396 | BE55: 0 | BF55: 0.122 | BG55: 0 | BH55: 0.1177 | BI55: 0.122 | BJ55: 0 | BK55: Yes | BL55: Image; HAI = tree
A56: Carton_2020 | B56: 43 | C56: 1 | D56: 3 | E56: 3 | F56: 43.1 | G56: 43.1.3.3 | H56: Feature-based explanations don't help people detect misclassifications of online toxicity | I56: Carton, Samuel; Mei, Qiaozhu; Resnick, Paul | J56: 2020 | K56: Communication | L56: Proceedings of the international AAAI conference on web and social media | M56: Between-Subjects | N56: Independent Samples | O56: Classify toxic comments | P56: =VLOOKUP(O56,Sheet3!$A$1:$B$22,2,0) -> Review Analysis | Q56: Text | R56: No | S56: No | T56: No | U56: No | V56: Yes | W56: No | X56: Categoric | Y56: Categoric | Z56: Decide | AA56: Deep | AB56: Text | AC56: Categorical | AD56: Deep | AE56: Human | AF56: No | AG56: HAI = Pred + partial exp | AH56: Yes | AI56: No | AJ56: Image, Text | AK56: FPR | AL56: Error Rate | AM56: Down | AN56: 480 | AO56: 80 | AP56: 80 | AQ56: Crowdworkers | AR56: Crowdworkers | AS56: MTurk | AT56: No | AU56: Yes | AV56: 0.179 | AW56: 0.229 | AX56: 0.116 | AY56: -0.179 | AZ56: -0.229 | BA56: -0.116 | BB56: Human | BC56: -0.179 | BD56: -0.229 | BE56: 1 | BF56: 0.096 | BG56: 0 | BH56: 0.0791 | BI56: 0.096 | BJ56: 0 | BK56: Yes | BL56: Image; HAI = graph
A57: Carton_2020 | B57: 43 | C57: 1 | D57: 4 | E57: 1 | F57: 43.1 | G57: 43.1.4.1 | H57: Feature-based explanations don't help people detect misclassifications of online toxicity | I57: Carton, Samuel; Mei, Qiaozhu; Resnick, Paul | J57: 2020 | K57: Communication | L57: Proceedings of the international AAAI conference on web and social media | M57: Between-Subjects | N57: Independent Samples | O57: Classify toxic comments | P57: =VLOOKUP(O57,Sheet3!$A$1:$B$22,2,0) -> Review Analysis | Q57: Text | R57: No | S57: No | T57: No | U57: No | V57: Yes | W57: No | X57: Categoric | Y57: Categoric | Z57: Decide | AA57: Deep | AB57: Text | AC57: Categorical | AD57: Deep | AE57: Human | AF57: No | AG57: HAI = keyword exp | AH57: Yes | AI57: No | AJ57: Image, Text | AK57: Accuracy | AL57: Accuracy | AM57: Up | AN57: 480 | AO57: 80 | AP57: 80 | AQ57: Crowdworkers | AR57: Crowdworkers | AS57: MTurk | AT57: No | AU57: Yes | AV57: 0.544 | AW57: 0.375 | AX57: 0.518 | AY57: 0.544 | AZ57: 0.375 | BA57: 0.518 | BB57: Human | BC57: 0.544 | BD57: 0.375 | BE57: 0 | BF57: 0.115 | BG57: 0 | BH57: 0.1065 | BI57: 0.115 | BJ57: 0 | BK57: Yes | BL57: Roses; HAI = grid
A58: Carton_2020 | B58: 43 | C58: 1 | D58: 4 | E58: 2 | F58: 43.1 | G58: 43.1.4.2 | H58: Feature-based explanations don't help people detect misclassifications of online toxicity | I58: Carton, Samuel; Mei, Qiaozhu; Resnick, Paul | J58: 2020 | K58: Communication | L58: Proceedings of the international AAAI conference on web and social media | M58: Between-Subjects | N58: Independent Samples | O58: Classify toxic comments | P58: =VLOOKUP(O58,Sheet3!$A$1:$B$22,2,0) -> Review Analysis | Q58: Text | R58: No | S58: No | T58: No | U58: No | V58: Yes | W58: No | X58: Categoric | Y58: Categoric | Z58: Decide | AA58: Deep | AB58: Text | AC58: Categorical | AD58: Deep | AE58: Human | AF58: No | AG58: HAI = keyword exp | AH58: Yes | AI58: No | AJ58: Image, Text | AK58: FNR | AL58: Error Rate | AM58: Down | AN58: 480 | AO58: 80 | AP58: 80 | AQ58: Crowdworkers | AR58: Crowdworkers | AS58: MTurk | AT58: No | AU58: Yes | AV58: 0.276 | AW58: 0.396 | AX58: 0.346 | AY58: -0.276 | AZ58: -0.396 | BA58: -0.346 | BB58: Human | BC58: -0.276 | BD58: -0.396 | BE58: 0 | BF58: 0.122 | BG58: 0 | BH58: 0.1164 | BI58: 0.122 | BJ58: 0 | BK58: Yes | BL58: Roses; HAI = tree
A59: Carton_2020 | B59: 43 | C59: 1 | D59: 4 | E59: 3 | F59: 43.1 | G59: 43.1.4.3 | H59: Feature-based explanations don't help people detect misclassifications of online toxicity | I59: Carton, Samuel; Mei, Qiaozhu; Resnick, Paul | J59: 2020 | K59: Communication | L59: Proceedings of the international AAAI conference on web and social media | M59: Between-Subjects | N59: Independent Samples | O59: Classify toxic comments | P59: =VLOOKUP(O59,Sheet3!$A$1:$B$22,2,0) -> Review Analysis | Q59: Text | R59: No | S59: No | T59: No | U59: No | V59: Yes | W59: No | X59: Categoric | Y59: Categoric | Z59: Decide | AA59: Deep | AB59: Text | AC59: Categorical | AD59: Deep | AE59: Human | AF59: No | AG59: HAI = keyword exp | AH59: Yes | AI59: No | AJ59: Image, Text | AK59: FPR | AL59: Error Rate | AM59: Down | AN59: 480 | AO59: 80 | AP59: 80 | AQ59: Crowdworkers | AR59: Crowdworkers | AS59: MTurk | AT59: No | AU59: Yes | AV59: 0.179 | AW59: 0.229 | AX59: 0.135 | AY59: -0.179 | AZ59: -0.229 | BA59: -0.135 | BB59: Human | BC59: -0.179 | BD59: -0.229 | BE59: 1 | BF59: 0.096 | BG59: 0 | BH59: 0.0938 | BI59: 0.096 | BJ59: 0 | BK59: Yes | BL59: Roses; HAI = graph
A60: Carton_2020 | B60: 43 | C60: 1 | D60: 5 | E60: 1 | F60: 43.1 | G60: 43.1.5.1 | H60: Feature-based explanations don't help people detect misclassifications of online toxicity | I60: Carton, Samuel; Mei, Qiaozhu; Resnick, Paul | J60: 2020 | K60: Communication | L60: Proceedings of the international AAAI conference on web and social media | M60: Between-Subjects | N60: Independent Samples | O60: Classify toxic comments | P60: =VLOOKUP(O60,Sheet3!$A$1:$B$22,2,0) -> Review Analysis | Q60: Text | R60: No | S60: No | T60: No | U60: No | V60: Yes | W60: No | X60: Categoric | Y60: Categoric | Z60: Decide | AA60: Deep | AB60: Text | AC60: Categorical | AD60: Deep | AE60: Human | AF60: No | AG60: HAI = No pred + full exp | AH60: Yes | AI60: No | AJ60: Image, Text | AK60: Accuracy | AL60: Accuracy | AM60: Up | AN60: 480 | AO60: 80 | AP60: 80 | AQ60: Crowdworkers | AR60: Crowdworkers | AS60: MTurk | AT60: No | AU60: Yes | AV60: 0.544 | AW60: 0.375 | AX60: 0.514 | AY60: 0.544 | AZ60: 0.375 | BA60: 0.514 | BB60: Human | BC60: 0.544 | BD60: 0.375 | BE60: 0 | BF60: 0.115 | BG60: 0 | BH60: 0.116 | BI60: 0.115 | BJ60: 0 | BK60: Yes | BL60: Non-anchor
A61: Carton_2020 | B61: 43 | C61: 1 | D61: 5 | E61: 2 | F61: 43.1 | G61: 43.1.5.2 | H61: Feature-based explanations don't help people detect misclassifications of online toxicity | I61: Carton, Samuel; Mei, Qiaozhu; Resnick, Paul | J61: 2020 | K61: Communication | L61: Proceedings of the international AAAI conference on web and social media | M61: Between-Subjects | N61: Independent Samples | O61: Classify toxic comments | P61: =VLOOKUP(O61,Sheet3!$A$1:$B$22,2,0) -> Review Analysis | Q61: Text | R61: No | S61: No | T61: No | U61: No | V61: Yes | W61: No | X61: Categoric | Y61: Categoric | Z61: Decide | AA61: Deep | AB61: Text | AC61: Categorical | AD61: Deep | AE61: Human | AF61: No | AG61: HAI = No pred + full exp | AH61: Yes | AI61: No | AJ61: Image, Text | AK61: FNR | AL61: Error Rate | AM61: Down | AN61: 480 | AO61: 80 | AP61: 80 | AQ61: Crowdworkers | AR61: Crowdworkers | AS61: MTurk | AT61: No | AU61: Yes | AV61: 0.276 | AW61: 0.396 | AX61: 0.353 | AY61: -0.276 | AZ61: -0.396 | BA61: -0.353 | BB61: Human | BC61: -0.276 | BD61: -0.396 | BE61: 0 | BF61: 0.122 | BG61: 0 | BH61: 0.13 | BI61: 0.122 | BJ61: 0 | BK61: Yes | BL61: Non-anchor
A62: Carton_2020 | B62: 43 | C62: 1 | D62: 5 | E62: 3 | F62: 43.1 | G62: 43.1.5.3 | H62: Feature-based explanations don't help people detect misclassifications of online toxicity | I62: Carton, Samuel; Mei, Qiaozhu; Resnick, Paul | J62: 2020 | K62: Communication | L62: Proceedings of the international AAAI conference on web and social media | M62: Between-Subjects | N62: Independent Samples | O62: Classify toxic comments | P62: =VLOOKUP(O62,Sheet3!$A$1:$B$22,2,0) -> Review Analysis | Q62: Text | R62: No | S62: No | T62: No | U62: No | V62: Yes | W62: No | X62: Categoric | Y62: Categoric | Z62: Decide | AA62: Deep | AB62: Text | AC62: Categorical | AD62: Deep | AE62: Human | AF62: No | AG62: HAI = No pred + full exp | AH62: Yes | AI62: No | AJ62: Image, Text | AK62: FPR | AL62: Error Rate | AM62: Down | AN62: 480 | AO62: 80 | AP62: 80 | AQ62: Crowdworkers | AR62: Crowdworkers | AS62: MTurk | AT62: No | AU62: Yes | AV62: 0.179 | AW62: 0.229 | AX62: 0.133 | AY62: -0.179 | AZ62: -0.229 | BA62: -0.133 | BB62: Human | BC62: -0.179 | BD62: -0.229 | BE62: 1 | BF62: 0.096 | BG62: 0 | BH62: 0.1029 | BI62: 0.096 | BJ62: 0 | BK62: Yes | BL62: Non-anchor
A63: Lai_2020 | B63: 1 | C63: 1 | D63: 1 | E63: 1 | F63: 1.1 | G63: 1.1.1.1 | H63: "Why is 'Chicago' Deceptive?" Towards Building Model-Driven Tutorials for Humans | I63: Lai, Vivian; Liu, Han; Tan, Chenhao | J63: 2020 | K63: Communication | L63: Proceedings of the 2020 CHI Conference on Human Factors in Computing Systems | M63: Between-Subjects | N63: Independent Samples | O63: Detect deceptive hotel reviews | P63: =VLOOKUP(O63,Sheet3!$A$1:$B$22,2,0) -> Review Analysis | Q63: Text | R63: No | S63: No | T63: No | U63: No | V63: Yes | W63: No | X63: Binary | Y63: Binary | Z63: Decide | AA63: Shallow | AB63: Text | AC63: Text | AD63: Rule-Based | AE63: Human | AF63: No | AG63: HAI = Guidelines | AH63: No | AI63: No | AK63: Accuracy | AL63: Accuracy | AM63: Up | AN63: 480 | AO63: 80 | AP63: 80 | AQ63: Crowdworkers | AR63: Crowdworkers | AS63: MTurk | AT63: No | AU63: Yes | AV63: 0.546 | AW63: 0.863 | AX63: 0.604 | AY63: 0.546 | AZ63: 0.863 | BA63: 0.604 | BB63: AI | BC63: 0.863 | BD63: 0.546 | BE63: 0 | BF63: 0.3043 | BG63: 0 | BH63: 0.30526769 | BI63: 0 | BJ63: 0.3043 | BK63: Yes | BL63: HAI = Guidelines
A64: Lai_2020 | B64: 1 | C64: 1 | D64: 2 | E64: 1 | F64: 1.1 | G64: 1.1.2.1 | H64: "Why is 'Chicago' Deceptive?" Towards Building Model-Driven Tutorials for Humans | I64: Lai, Vivian; Liu, Han; Tan, Chenhao | J64: 2020 | K64: Communication | L64: Proceedings of the 2020 CHI Conference on Human Factors in Computing Systems | M64: Between-Subjects | N64: Independent Samples | O64: Detect deceptive hotel reviews | P64: =VLOOKUP(O64,Sheet3!$A$1:$B$22,2,0) -> Review Analysis | Q64: Text | R64: No | S64: No | T64: No | U64: No | V64: Yes | W64: No | X64: Binary | Y64: Binary | Z64: Decide | AA64: Shallow | AB64: Text | AC64: Text | AD64: Rule-Based | AE64: Human | AF64: No | AG64: HAI = Random explanation | AH64: No | AI64: No | AK64: Accuracy | AL64: Accuracy | AM64: Up | AN64: 480 | AO64: 80 | AP64: 80 | AQ64: Crowdworkers | AR64: Crowdworkers | AS64: MTurk | AT64: No | AU64: Yes | AV64: 0.546 | AW64: 0.863 | AX64: 0.609 | AY64: 0.546 | AZ64: 0.863 | BA64: 0.609 | BB64: AI | BC64: 0.863 | BD64: 0.546 | BE64: 0 | BF64: 0.3043 | BG64: 0 | BH64: 0.27409611 | BI64: 0 | BJ64: 0.3043 | BK64: Yes | BL64: HAI = Random explanation
A65: Lai_2020 | B65: 1 | C65: 1 | D65: 3 | E65: 1 | F65: 1.1 | G65: 1.1.3.1 | H65: "Why is 'Chicago' Deceptive?" Towards Building Model-Driven Tutorials for Humans | I65: Lai, Vivian; Liu, Han; Tan, Chenhao | J65: 2020 | K65: Communication | L65: Proceedings of the 2020 CHI Conference on Human Factors in Computing Systems | M65: Between-Subjects | N65: Independent Samples | O65: Detect deceptive hotel reviews | P65: =VLOOKUP(O65,Sheet3!$A$1:$B$22,2,0) -> Review Analysis | Q65: Text | R65: No | S65: No | T65: No | U65: No | V65: Yes | W65: No | X65: Binary | Y65: Binary | Z65: Decide | AA65: Shallow | AB65: Text | AC65: Text | AD65: Rule-Based | AE65: Human | AF65: No | AG65: HAI = SP-LIME | AH65: No | AI65: No | AK65: Accuracy | AL65: Accuracy | AM65: Up | AN65: 480 | AO65: 80 | AP65: 80 | AQ65: Crowdworkers | AR65: Crowdworkers | AS65: MTurk | AT65: No | AU65: Yes | AV65: 0.546 | AW65: 0.863 | AX65: 0.578 | AY65: 0.546 | AZ65: 0.863 | BA65: 0.578 | BB65: AI | BC65: 0.863 | BD65: 0.546 | BE65: 0 | BF65: 0.3043 | BG65: 0 | BH65: 0.29473176 | BI65: 0 | BJ65: 0.3043 | BK65: Yes | BL65: HAI = SP-LIME
A66: Lai_2020 | B66: 1 | C66: 1 | D66: 4 | E66: 1 | F66: 1.1 | G66: 1.1.4.1 | H66: "Why is 'Chicago' Deceptive?" Towards Building Model-Driven Tutorials for Humans | I66: Lai, Vivian; Liu, Han; Tan, Chenhao | J66: 2020 | K66: Communication | L66: Proceedings of the 2020 CHI Conference on Human Factors in Computing Systems | M66: Between-Subjects | N66: Independent Samples | O66: Detect deceptive hotel reviews | P66: =VLOOKUP(O66,Sheet3!$A$1:$B$22,2,0) -> Review Analysis | Q66: Text | R66: No | S66: No | T66: No | U66: No | V66: Yes | W66: No | X66: Binary | Y66: Binary | Z66: Decide | AA66: Shallow | AB66: Text | AC66: Text | AD66: Rule-Based | AE66: Human | AF66: No | AG66: HAI = SR | AH66: No | AI66: No | AK66: Accuracy | AL66: Accuracy | AM66: Up | AN66: 480 | AO66: 80 | AP66: 80 | AQ66: Crowdworkers | AR66: Crowdworkers | AS66: MTurk | AT66: No | AU66: Yes | AV66: 0.546 | AW66: 0.863 | AX66: 0.579 | AY66: 0.546 | AZ66: 0.863 | BA66: 0.579 | BB66: AI | BC66: 0.863 | BD66: 0.546 | BE66: 0 | BF66: 0.3043 | BG66: 0 | BH66: 0.24389167 | BI66: 0 | BJ66: 0.3043 | BK66: Yes | BL66: HAI = SR
A67: Lai_2020 | B67: 1 | C67: 1 | D67: 5 | E67: 1 | F67: 1.1 | G67: 1.1.5.1 | H67: "Why is 'Chicago' Deceptive?" Towards Building Model-Driven Tutorials for Humans | I67: Lai, Vivian; Liu, Han; Tan, Chenhao | J67: 2020 | K67: Communication | L67: Proceedings of the 2020 CHI Conference on Human Factors in Computing Systems | M67: Between-Subjects | N67: Independent Samples | O67: Detect deceptive hotel reviews | P67: =VLOOKUP(O67,Sheet3!$A$1:$B$22,2,0) -> Review Analysis | Q67: Text | R67: No | S67: No | T67: No | U67: No | V67: Yes | W67: No | X67: Binary | Y67: Binary | Z67: Decide | AA67: Shallow | AB67: Text | AC67: Text | AD67: Rule-Based | AE67: Human | AF67: No | AG67: HAI = SR + guidelines | AH67: No | AI67: No | AK67: Accuracy | AL67: Accuracy | AM67: Up | AN67: 480 | AO67: 80 | AP67: 80 | AQ67: Crowdworkers | AR67: Crowdworkers | AS67: MTurk | AT67: No | AU67: Yes | AV67: 0.546 | AW67: 0.863 | AX67: 0.592 | AY67: 0.546 | AZ67: 0.863 | BA67: 0.592 | BB67: AI | BC67: 0.863 | BD67: 0.546 | BE67: 0 | BF67: 0.3043 | BG67: 0 | BH67: 0.27508047 | BI67: 0 | BJ67: 0.3043 | BK67: Yes | BL67: HAI = SR + guidelines
A68: Lai_2020 | B68: 1 | C68: 2 | D68: 1 | E68: 1 | F68: 1.2 | G68: 1.2.1.1 | H68: "Why is 'Chicago' Deceptive?" Towards Building Model-Driven Tutorials for Humans | I68: Lai, Vivian; Liu, Han; Tan, Chenhao | J68: 2020 | K68: Communication | L68: Proceedings of the 2020 CHI Conference on Human Factors in Computing Systems | M68: Between-Subjects | N68: Independent Samples | O68: Detect deceptive hotel reviews | P68: =VLOOKUP(O68,Sheet3!$A$1:$B$22,2,0) -> Review Analysis | Q68: Text | R68: No | S68: No | T68: No | U68: No | V68: Yes | W68: No | X68: Binary | Y68: Binary | Z68: Decide | AA68: Shallow | AB68: Text | AC68: Text | AD68: Rule-Based | AE68: Human | AF68: No | AG68: HAI = Unigned | AH68: Yes | AI68: No | AJ68: Image, Text | AK68: Accuracy | AL68: Accuracy | AM68: Up | AN68: 480 | AO68: 80 | AP68: 80 | AQ68: Crowdworkers | AR68: Crowdworkers | AS68: MTurk | AT68: No | AU68: Yes | AV68: 0.604 | AW68: 0.863 | AX68: 0.578 | AY68: 0.604 | AZ68: 0.863 | BA68: 0.578 | BB68: AI | BC68: 0.863 | BD68: 0.604 | BE68: 0 | BF68: 0.2756 | BG68: 0 | BH68: 0.21768708 | BI68: 0 | BJ68: 0.2756 | BK68: Yes | BL68: HAI = Unigned
A69: Lai_2020 | B69: 1 | C69: 2 | D69: 2 | E69: 1 | F69: 1.2 | G69: 1.2.2.1 | H69: "Why is 'Chicago' Deceptive?" Towards Building Model-Driven Tutorials for Humans | I69: Lai, Vivian; Liu, Han; Tan, Chenhao | J69: 2020 | K69: Communication | L69: Proceedings of the 2020 CHI Conference on Human Factors in Computing Systems | M69: Between-Subjects | N69: Independent Samples | O69: Detect deceptive hotel reviews | P69: =VLOOKUP(O69,Sheet3!$A$1:$B$22,2,0) -> Review Analysis | Q69: Text | R69: No | S69: No | T69: No | U69: No | V69: Yes | W69: No | X69: Binary | Y69: Binary | Z69: Decide | AA69: Shallow | AB69: Text | AC69: Text | AD69: Rule-Based | AE69: Human | AF69: No | AG69: HAI = Signed | AH69: Yes | AI69: No | AJ69: Image, Text | AK69: Accuracy | AL69: Accuracy | AM69: Up | AN69: 480 | AO69: 80 | AP69: 80 | AQ69: Crowdworkers | AR69: Crowdworkers | AS69: MTurk | AT69: No | AU69: Yes | AV69: 0.604 | AW69: 0.863 | AX69: 0.707 | AY69: 0.604 | AZ69: 0.863 | BA69: 0.707 | BB69: AI | BC69: 0.863 | BD69: 0.604 | BE69: 0 | BF69: 0.2756 | BG69: 0 | BH69: 0.21900373 | BI69: 0 | BJ69: 0.2756 | BK69: Yes | BL69: HAI = Signed
A70: Lai_2020 | B70: 1 | C70: 2 | D70: 3 | E70: 1 | F70: 1.2 | G70: 1.2.3.1 | H70: "Why is 'Chicago' Deceptive?" Towards Building Model-Driven Tutorials for Humans | I70: Lai, Vivian; Liu, Han; Tan, Chenhao | J70: 2020 | K70: Communication | L70: Proceedings of the 2020 CHI Conference on Human Factors in Computing Systems | M70: Between-Subjects | N70: Independent Samples | O70: Detect deceptive hotel reviews | P70: =VLOOKUP(O70,Sheet3!$A$1:$B$22,2,0) -> Review Analysis | Q70: Text | R70: No | S70: No | T70: No | U70: No | V70: Yes | W70: No | X70: Binary | Y70: Binary | Z70: Decide | AA70: Shallow | AB70: Text | AC70: Text | AD70: Rule-Based | AE70: Human | AF70: No | AG70: HAI = Signed + predicted label | AH70: Yes | AI70: No | AJ70: Image, Numeric | AK70: Accuracy | AL70: Accuracy | AM70: Up | AN70: 480 | AO70: 80 | AP70: 80 | AQ70: Crowdworkers | AR70: Crowdworkers | AS70: MTurk | AT70: No | AU70: Yes | AV70: 0.604 | AW70: 0.863 | AX70: 0.723 | AY70: 0.604 | AZ70: 0.863 | BA70: 0.723 | BB70: AI | BC70: 0.863 | BD70: 0.604 | BE70: 0 | BF70: 0.2756 | BG70: 0 | BH70: 0.26815888 | BI70: 0 | BJ70: 0.2756 | BK70: Yes | BL70: HAI = Signed + predicted label
A71: Lai_2020 | B71: 1 | C71: 2 | D71: 4 | E71: 1 | F71: 1.2 | G71: 1.2.4.1 | H71: "Why is 'Chicago' Deceptive?" Towards Building Model-Driven Tutorials for Humans | I71: Lai, Vivian; Liu, Han; Tan, Chenhao | J71: 2020 | K71: Communication | L71: Proceedings of the 2020 CHI Conference on Human Factors in Computing Systems | M71: Between-Subjects | N71: Independent Samples | O71: Detect deceptive hotel reviews | P71: =VLOOKUP(O71,Sheet3!$A$1:$B$22,2,0) -> Review Analysis | Q71: Text | R71: No | S71: No | T71: No | U71: No | V71: Yes | W71: No | X71: Binary | Y71: Binary | Z71: Decide | AA71: Shallow | AB71: Text | AC71: Text | AD71: Rule-Based | AE71: Human | AF71: No | AG71: HAI = Signed + predicted label + guidelines | AH71: Yes | AI71: No | AJ71: Image, Numeric, Text | AK71: Accuracy | AL71: Accuracy | AM71: Up | AN71: 480 | AO71: 80 | AP71: 80 | AQ71: Crowdworkers | AR71: Crowdworkers | AS71: MTurk | AT71: No | AU71: Yes | AV71: 0.604 | AW71: 0.863 | AX71: 0.705 | AY71: 0.604 | AZ71: 0.863 | BA71: 0.705 | BB71: AI | BC71: 0.863 | BD71: 0.604 | BE71: 0 | BF71: 0.2756 | BG71: 0 | BH71: 0.25674786 | BI71: 0 | BJ71: 0.2756 | BK71: Yes | BL71: HAI = Signed + predicted label + guidelines
A72: Lai_2020 | B72: 1 | C72: 2 | D72: 5 | E72: 1 | F72: 1.2 | G72: 1.2.5.1 | H72: "Why is 'Chicago' Deceptive?" Towards Building Model-Driven Tutorials for Humans | I72: Lai, Vivian; Liu, Han; Tan, Chenhao | J72: 2020 | K72: Communication | L72: Proceedings of the 2020 CHI Conference on Human Factors in Computing Systems | M72: Between-Subjects | N72: Independent Samples | O72: Detect deceptive hotel reviews | P72: =VLOOKUP(O72,Sheet3!$A$1:$B$22,2,0) -> Review Analysis | Q72: Text | R72: No | S72: No | T72: No | U72: No | V72: Yes | W72: No | X72: Binary | Y72: Binary | Z72: Decide | AA72: Shallow | AB72: Text | AC72: Text | AD72: Rule-Based | AE72: Human | AF72: No | AG72: HAI = Signed + predicted label + guidelines + accuracy | AH72: Yes | AI72: No | AJ72: Image, Numeric, Text | AK72: Accuracy | AL72: Accuracy | AM72: Up | AN72: 480 | AO72: 80 | AP72: 80 | AQ72: Crowdworkers | AR72: Crowdworkers | AS72: MTurk | AT72: No | AU72: Yes | AV72: 0.604 | AW72: 0.863 | AX72: 0.74 | AY72: 0.604 | AZ72: 0.863 | BA72: 0.74 | BB72: AI | BC72: 0.863 | BD72: 0.604 | BE72: 0 | BF72: 0.2756 | BG72: 0 | BH72: 0.2764977 | BI72: 0 | BJ72: 0.2756 | BK72: Yes | BL72: HAI = Signed + predicted label + guidelines + accuracy
A73: Lai_2020 | B73: 1 | C73: 3 | D73: 1 | E73: 1 | F73: 1.3 | G73: 1.3.1.1 | H73: "Why is 'Chicago' Deceptive?" Towards Building Model-Driven Tutorials for Humans | I73: Lai, Vivian; Liu, Han; Tan, Chenhao | J73: 2020 | K73: Communication | L73: Proceedings of the 2020 CHI Conference on Human Factors in Computing Systems | M73: Between-Subjects | N73: Independent Samples | O73: Detect deceptive hotel reviews | P73: =VLOOKUP(O73,Sheet3!$A$1:$B$22,2,0) -> Review Analysis | Q73: Text | R73: No | S73: No | T73: No | U73: No | V73: Yes | W73: No | X73: Binary | Y73: Binary | Z73: Decide | AA73: Shallow | AB73: Text | AC73: Text | AD73: Rule-Based | AE73: Human | AF73: No | AG73: HAI = SVM, no training | AH73: Yes | AI73: No | AJ73: Image, Text | AK73: Accuracy | AL73: Accuracy | AM73: Up | AN73: 480 | AO73: 80 | AP73: 80 | AQ73: Crowdworkers | AR73: Crowdworkers | AS73: MTurk | AT73: No | AU73: Yes | AV73: 0.546 | AW73: 0.863 | AX73: 0.641 | AY73: 0.546 | AZ73: 0.863 | BA73: 0.641 | BB73: AI | BC73: 0.863 | BD73: 0.546 | BE73: 0 | BF73: 0.2756 | BG73: 0 | BH73: 0.53745092 | BI73: 0 | BJ73: 0.2756 | BK73: Yes | BL73: HAI = SVM, no training
A74: Lai_2020 | B74: 1 | C74: 3 | D74: 2 | E74: 1 | F74: 1.3 | G74: 1.3.2.1 | H74: "Why is 'Chicago' Deceptive?" Towards Building Model-Driven Tutorials for Humans | I74: Lai, Vivian; Liu, Han; Tan, Chenhao | J74: 2020 | K74: Communication | L74: Proceedings of the 2020 CHI Conference on Human Factors in Computing Systems | M74: Between-Subjects | N74: Independent Samples | O74: Detect deceptive hotel reviews | P74: =VLOOKUP(O74,Sheet3!$A$1:$B$22,2,0) -> Review Analysis | Q74: Text | R74: No | S74: No | T74: No | U74: No | V74: Yes | W74: No | X74: Binary | Y74: Binary | Z74: Decide | AA74: Shallow | AB74: Text | AC74: Text | AD74: Rule-Based | AE74: Human | AF74: No | AG74: HAI = SVM, training | AH74: Yes | AI74: No | AJ74: Image, Text | AK74: Accuracy | AL74: Accuracy | AM74: Up | AN74: 480 | AO74: 80 | AP74: 80 | AQ74: Crowdworkers | AR74: Crowdworkers | AS74: MTurk | AT74: No | AU74: Yes | AV74: 0.546 | AW74: 0.863 | AX74: 0.728 | AY74: 0.546 | AZ74: 0.863 | BA74: 0.728 | BB74: AI | BC74: 0.863 | BD74: 0.546 | BE74: 0 | BF74: 0.2756 | BG74: 0 | BH74: 0.45997109 | BI74: 0 | BJ74: 0.2756 | BK74: Yes | BL74: HAI = SVM, training
A75: Lai_2020 | B75: 1 | C75: 3 | D75: 3 | E75: 1 | F75: 1.3 | G75: 1.3.3.1 | H75: "Why is 'Chicago' Deceptive?" Towards Building Model-Driven Tutorials for Humans | I75: Lai, Vivian; Liu, Han; Tan, Chenhao | J75: 2020 | K75: Communication | L75: Proceedings of the 2020 CHI Conference on Human Factors in Computing Systems | M75: Between-Subjects | N75: Independent Samples | O75: Detect deceptive hotel reviews | P75: =VLOOKUP(O75,Sheet3!$A$1:$B$22,2,0) -> Review Analysis | Q75: Text | R75: No | S75: No | T75: No | U75: No | V75: Yes | W75: No | X75: Binary | Y75: Binary | Z75: Decide | AA75: Deep | AB75: Text | AC75: Text | AD75: Deep | AE75: Human | AF75: No | AG75: HAI = BERT-ATT, no training | AH75: Yes | AI75: No | AJ75: Image, Text | AK75: Accuracy | AL75: Accuracy | AM75: Up | AN75: 480 | AO75: 80 | AP75: 80 | AQ75: Crowdworkers | AR75: Crowdworkers | AS75: MTurk | AT75: No | AU75: Yes | AV75: 0.546 | AW75: 0.909 | AX75: 0.541 | AY75: 0.546 | AZ75: 0.909 | BA75: 0.541 | BB75: AI | BC75: 0.909 | BD75: 0.546 | BE75: 0 | BF75: 0.3043 | BG75: 0 | BH75: 0.39976054 | BI75: 0 | BJ75: 0.3043 | BK75: Yes | BL75: HAI = BERT-ATT, no training
A76: Lai_2020 | B76: 1 | C76: 3 | D76: 4 | E76: 1 | F76: 1.3 | G76: 1.3.4.1 | H76: "Why is 'Chicago' Deceptive?" Towards Building Model-Driven Tutorials for Humans | I76: Lai, Vivian; Liu, Han; Tan, Chenhao | J76: 2020 | K76: Communication | L76: Proceedings of the 2020 CHI Conference on Human Factors in Computing Systems | M76: Between-Subjects | N76: Independent Samples | O76: Detect deceptive hotel reviews | P76: =VLOOKUP(O76,Sheet3!$A$1:$B$22,2,0) -> Review Analysis | Q76: Text | R76: No | S76: No | T76: No | U76: No | V76: Yes | W76: No | X76: Binary | Y76: Binary | Z76: Decide | AA76: Deep | AB76: Text | AC76: Text | AD76: Deep | AE76: Human | AF76: No | AG76: HAI = BERT-ATT, training | AH76: Yes | AI76: No | AJ76: Image, Text | AK76: Accuracy | AL76: Accuracy | AM76: Up | AN76: 480 | AO76: 80 | AP76: 80 | AQ76: Crowdworkers | AR76: Crowdworkers | AS76: MTurk | AT76: No | AU76: Yes | AV76: 0.546 | AW76: 0.909 | AX76: 0.582 | AY76: 0.546 | AZ76: 0.909 | BA76: 0.582 | BB76: AI | BC76: 0.909 | BD76: 0.546 | BE76: 0 | BF76: 0.3043 | BG76: 0 | BH76: 0.36239591 | BI76: 0 | BJ76: 0.3043 | BK76: Yes | BL76: HAI = BERT-ATT, training
A77: Lai_2020 | B77: 1 | C77: 3 | D77: 5 | E77: 1 | F77: 1.3 | G77: 1.3.5.1 | H77: "Why is 'Chicago' Deceptive?" Towards Building Model-Driven Tutorials for Humans | I77: Lai, Vivian; Liu, Han; Tan, Chenhao | J77: 2020 | K77: Communication | L77: Proceedings of the 2020 CHI Conference on Human Factors in Computing Systems | M77: Between-Subjects | N77: Independent Samples | O77: Detect deceptive hotel reviews | P77: =VLOOKUP(O77,Sheet3!$A$1:$B$22,2,0) -> Review Analysis | Q77: Text | R77: No | S77: No | T77: No | U77: No | V77: Yes | W77: No | X77: Binary | Y77: Binary | Z77: Decide | AA77: Deep | AB77: Text | AC77: Text | AD77: Deep | AE77: Human | AF77: No | AG77: HAI = BERT-LIME, no training | AH77: Yes | AI77: No | AJ77: Image, Text | AK77: Accuracy | AL77: Accuracy | AM77: Up | AN77: 480 | AO77: 80 | AP77: 80 | AQ77: Crowdworkers | AR77: Crowdworkers | AS77: MTurk | AT77: No | AU77: Yes | AV77: 0.546 | AW77: 0.909 | AX77: 0.592 | AY77: 0.546 | AZ77: 0.909 | BA77: 0.592 | BB77: AI | BC77: 0.909 | BD77: 0.546 | BE77: 0 | BF77: 0.3043 | BG77: 0 | BH77: 0.35042283 | BI77: 0 | BJ77: 0.3043 | BK77: Yes | BL77: HAI = BERT-LIME, no training
A78: Lai_2020 | B78: 1 | C78: 3 | D78: 6 | E78: 1 | F78: 1.3 | G78: 1.3.6.1 | H78: "Why is 'Chicago' Deceptive?" Towards Building Model-Driven Tutorials for Humans | I78: Lai, Vivian; Liu, Han; Tan, Chenhao | J78: 2020 | K78: Communication | L78: Proceedings of the 2020 CHI Conference on Human Factors in Computing Systems | M78: Between-Subjects | N78: Independent Samples | O78: Detect deceptive hotel reviews | P78: =VLOOKUP(O78,Sheet3!$A$1:$B$22,2,0) -> Review Analysis | Q78: Text | R78: No | S78: No | T78: No | U78: No | V78: Yes | W78: No | X78: Binary | Y78: Binary | Z78: Decide | AA78: Deep | AB78: Text | AC78: Text | AD78: Deep | AE78: Human | AF78: No | AG78: HAI = BERT-LIME, training | AH78: Yes | AI78: No | AJ78: Image, Text | AK78: Accuracy | AL78: Accuracy | AM78: Up | AN78: 480 | AO78: 80 | AP78: 80 | AQ78: Crowdworkers | AR78: Crowdworkers | AS78: MTurk | AT78: No | AU78: Yes | AV78: 0.546 | AW78: 0.909 | AX78: 0.649 | AY78: 0.546 | AZ78: 0.909 | BA78: 0.649 | BB78: AI | BC78: 0.909 | BD78: 0.546 | BE78: 0 | BF78: 0.3043 | BG78: 0 | BH78: 0.32790051 | BI78: 0 | BJ78: 0.3043 | BK78: Yes | BL78: HAI = BERT-LIME, training
A79: Jiang_2020 | B79: 3 | C79: 1 | D79: 1 | E79: 1 | F79: 3.1 | G79: 3.1.1.1 | H79: Response Quality in Human-Chatbot Collaborative Systems | I79: Jiang, Jiepu; Ahuja, Naman | J79: 2020 | K79: Communication | L79: Proceedings of the 43rd International ACM SIGIR Conference on Research and Development in Information Retrieval | M79: Between-Subjects | N79: Independent Samples | O79: Engage in a conversation | P79: =VLOOKUP(O79,Sheet3!$A$1:$B$22,2,0) -> Customer Service | Q79: Text | R79: No | S79: No | T79: No | U79: No | V79: Yes | W79: No | X79: Text | Y79: Open Response | Z79: Create | AA79: Deep | AB79: Text | AC79: Text | AD79: Deep | AE79: Human | AF79: No | AG79: HAI = C1, 1 suggestion | AH79: No | AI79: No | AK79: Informativeness | AL79: Quality | AM79: Up | AN79: 140 | AO79: 20 | AP79: 20 | AQ79: Crowdworkers | AR79: Crowdworkers | AS79: MTurk | AT79: No | AU79: Yes | AV79: 2.72 | AW79: 2.81 | AX79: 2.85 | AY79: 2.72 | AZ79: 2.81 | BA79: 2.85 | BB79: AI | BC79: 2.81 | BD79: 2.72 | BE79: 1 | BF79: 0.1 | BG79: 0.052094217 | BH79: 0.090961979 | BI79: 0.052094217 | BJ79: 0.1 | BK79: Yes | BL79: HAI = C1, 1 suggestion
A80: Jiang_2020 | B80: 3 | C80: 1 | D80: 2 | E80: 1 | F80: 3.1 | G80: 3.1.2.1 | H80: Response Quality in Human-Chatbot Collaborative Systems | I80: Jiang, Jiepu; Ahuja, Naman | J80: 2020 | K80: Communication | L80: Proceedings of the 43rd International ACM SIGIR Conference on Research and Development in Information Retrieval | M80: Between-Subjects | N80: Independent Samples | O80: Engage in a conversation | P80: =VLOOKUP(O80,Sheet3!$A$1:$B$22,2,0) -> Customer Service | Q80: Text | R80: No | S80: No | T80: No | U80: No | V80: Yes | W80: No | X80: Text | Y80: Open Response | Z80: Create | AA80: Deep | AB80: Text | AC80: Text | AD80: Deep | AE80: Human | AF80: No | AG80: HAI = C1, 3 suggestions | AH80: No | AI80: No | AK80: Informativeness | AL80: Quality | AM80: Up | AN80: 140 | AO80: 20 | AP80: 20 | AQ80: Crowdworkers | AR80: Crowdworkers | AS80: MTurk | AT80: No | AU80: Yes | AV80: 2.72 | AW80: 2.83 | AX80: 2.83 | AY80: 2.72 | AZ80: 2.83 | BA80: 2.83 | BB80: AI | BC80: 2.83 | BD80: 2.72 | BE80: 0 | BF80: 0.1 | BG80: 0.06773364 | BH80: 0.093629289 | BI80: 0.06773364 | BJ80: 0.1 | BK80: Yes | BL80: HAI = C1, 3 suggestions
A81: Jiang_2020 | B81: 3 | C81: 1 | D81: 3 | E81: 1 | F81: 3.1 | G81: 3.1.3.1 | H81: Response Quality in Human-Chatbot Collaborative Systems | I81: Jiang, Jiepu; Ahuja, Naman | J81: 2020 | K81: Communication | L81: Proceedings of the 43rd International ACM SIGIR Conference on Research and Development in Information Retrieval | M81: Between-Subjects | N81: Independent Samples | O81: Engage in a conversation | P81: =VLOOKUP(O81,Sheet3!$A$1:$B$22,2,0) -> Customer Service | Q81: Text | R81: No | S81: No | T81: No | U81: No | V81: Yes | W81: No | X81: Text | Y81: Open Response | Z81: Create | AA81: Deep | AB81: Text | AC81: Text | AD81: Deep | AE81: Human | AF81: No | AG81: HAI = C1, 5 suggestions | AH81: No | AI81: No | AK81: Informativeness | AL81: Quality | AM81: Up | AN81: 140 | AO81: 20 | AP81: 20 | AQ81: Crowdworkers | AR81: Crowdworkers | AS81: MTurk | AT81: No | AU81: Yes | AV81: 2.72 | AW81: 2.83 | AX81: 2.81 | AY81: 2.72 | AZ81: 2.83 | BA81: 2.81 | BB81: AI | BC81: 2.83 | BD81: 2.72 | BE81: 0 | BF81: 0.1 | BG81: 0.05661808 | BH81: 0.081824097 | BI81: 0.05661808 | BJ81: 0.1 | BK81: Yes | BL81: HAI = C1, 5 suggestions
A82: Jiang_2020 | B82: 3 | C82: 1 | D82: 4 | E82: 1 | F82: 3.1 | G82: 3.1.4.1 | H82: Response Quality in Human-Chatbot Collaborative Systems | I82: Jiang, Jiepu; Ahuja, Naman | J82: 2020 | K82: Communication | L82: Proceedings of the 43rd International ACM SIGIR Conference on Research and Development in Information Retrieval | M82: Between-Subjects | N82: Independent Samples | O82: Engage in a conversation | P82: =VLOOKUP(O82,Sheet3!$A$1:$B$22,2,0) -> Customer Service | Q82: Text | R82: No | S82: No | T82: No | U82: No | V82: Yes | W82: No | X82: Text | Y82: Open Response | Z82: Create | AA82: Deep | AB82: Text | AC82: Text | AD82: Deep | AE82: Human | AF82: No | AG82: HAI = C2, 1 suggestion | AH82: No | AI82: No | AK82: Informativeness | AL82: Quality | AM82: Up | AN82: 140 | AO82: 20 | AP82: 20 | AQ82: Crowdworkers | AR82: Crowdworkers | AS82: MTurk | AT82: No | AU82: Yes | AV82: 2.72 | AW82: 2.84 | AX82: 2.81 | AY82: 2.72 | AZ82: 2.84 | BA82: 2.81 | BB82: AI | BC82: 2.84 | BD82: 2.72 | BE82: 0 | BF82: 0.1 | BG82: 0.046323672 | BH82: 0.062016551 | BI82: 0.046323672 | BJ82: 0.1 | BK82: Yes | BL82: HAI = C2, 1 suggestion
A83: Jiang_2020 | B83: 3 | C83: 1 | D83: 5 | E83: 1 | F83: 3.1 | G83: 3.1.5.1 | H83: Response Quality in Human-Chatbot Collaborative Systems | I83: Jiang, Jiepu; Ahuja, Naman | J83: 2020 | K83: Communication | L83: Proceedings of the 43rd International ACM SIGIR Conference on Research and Development in Information Retrieval | M83: Between-Subjects | N83: Independent Samples | O83: Engage in a conversation | P83: =VLOOKUP(O83,Sheet3!$A$1:$B$22,2,0) -> Customer Service | Q83: Text | R83: No | S83: No | T83: No | U83: No | V83: Yes | W83: No | X83: Text | Y83: Open Response | Z83: Create | AA83: Deep | AB83: Text | AC83: Text | AD83: Deep | AE83: Human | AF83: No | AG83: HAI = C2, 3 suggestions | AH83: No | AI83: No | AK83: Informativeness | AL83: Quality | AM83: Up | AN83: 140 | AO83: 20 | AP83: 20 | AQ83: Crowdworkers | AR83: Crowdworkers | AS83: MTurk | AT83: No | AU83: Yes | AV83: 2.72 | AW83: 2.79 | AX83: 2.89 | AY83: 2.72 | AZ83: 2.79 | BA83: 2.89 | BB83: AI | BC83: 2.79 | BD83: 2.72 | BE83: 1 | BF83: 0.1 | BG83: 0.055015658 | BH83: 0.059477155 | BI83: 0.055015658 | BJ83: 0.1 | BK83: Yes | BL83: HAI = C2, 3 suggestions
A84: Jiang_2020 | B84: 3 | C84: 1 | D84: 6 | E84: 1 | F84: 3.1 | G84: 3.1.6.1 | H84: Response Quality in Human-Chatbot Collaborative Systems | I84: Jiang, Jiepu; Ahuja, Naman | J84: 2020 | K84: Communication | L84: Proceedings of the 43rd International ACM SIGIR Conference on Research and Development in Information Retrieval | M84: Between-Subjects | N84: Independent Samples | O84: Engage in a conversation | P84: =VLOOKUP(O84,Sheet3!$A$1:$B$22,2,0) -> Customer Service | Q84: Text | R84: No | S84: No | T84: No | U84: No | V84: Yes | W84: No | X84: Text | Y84: Open Response | Z84: Create | AA84: Deep | AB84: Text | AC84: Text | AD84: Deep | AE84: Human | AF84: No | AG84: HAI = C2, 5 suggestions | AH84: No | AI84: No | AK84: Informativeness | AL84: Quality | AM84: Up | AN84: 140 | AO84: 20 | AP84: 20 | AQ84: Crowdworkers | AR84: Crowdworkers | AS84: MTurk | AT84: No | AU84: Yes | AV84: 2.72 | AW84: 2.83 | AX84: 2.87 | AY84: 2.72 | AZ84: 2.83 | BA84: 2.87 | BB84: AI | BC84: 2.83 | BD84: 2.72 | BE84: 1 | BF84: 0.1 | BG84: 0.063712947 | BH84: 0.073732012 | BI84: 0.063712947 | BJ84: 0.1 | BK84: Yes | BL84: HAI = C2, 5 suggestions
A85: Bansal_2021 | B85: 6 | C85: 1 | D85: 1 | E85: 1 | F85: 6.1 | G85: 6.1.1.1 | H85: Does the Whole Exceed Its Parts? The Effect of AI Explanations on Complementary Team Performance | I85: Bansal, Gagan; Wu, Tongshuang; Zhou, Joyce; Fok, Raymond; Nushi, Besmira; Kamar, Ece; Ribeiro, Marco Tulio; Weld, Daniel | J85: 2021 | K85: Communication | L85: Proceedings of the 2021 CHI Conference on Human Factors in Computing Systems | M85: Between-Subjects | N85: Independent Samples | O85: Classify beer reviews | P85: =VLOOKUP(O85,Sheet3!$A$1:$B$22,2,0) -> Review Analysis | Q85: Text | R85: No | S85: No | T85: No | U85: No | V85: Yes | W85: No | X85: Binary | Y85: Binary | Z85: Decide | AA85: Deep | AB85: Text | AC85: Binary | AD85: Deep | AE85: Human | AF85: No | AG85: HAI = Beer, Conf | AH85: Yes | AI85: Yes | AJ85: Numeric | AK85: Accuracy | AL85: Accuracy | AM85: Up | AN85: 462 | AO85: 92 | AP85: 92 | AQ85: Crowdworkers | AR85: Crowdworkers | AS85: MTurk | AT85: No | AU85: Yes | AV85: 0.8157 | AW85: 0.84 | AX85: 0.8955 | AY85: 0.8157 | AZ85: 0.84 | BA85: 0.8955 | BB85: AI | BC85: 0.84 | BD85: 0.8157 | BE85: 1 | BF85: 0.0914 | BG85: 0 | BH85: 0.0473 | BI85: 0 | BJ85: 0.0914 | BK85: No | BL85: HAI = Conf
A86: Bansal_2021 | B86: 6 | C86: 1 | D86: 2 | E86: 1 | F86: 6.1 | G86: 6.1.2.1 | H86: Does the Whole Exceed Its Parts? The Effect of AI Explanations on Complementary Team Performance | I86: Bansal, Gagan; Wu, Tongshuang; Zhou, Joyce; Fok, Raymond; Nushi, Besmira; Kamar, Ece; Ribeiro, Marco Tulio; Weld, Daniel | J86: 2021 | K86: Communication | L86: Proceedings of the 2021 CHI Conference on Human Factors in Computing Systems | M86: Between-Subjects | N86: Independent Samples | O86: Classify beer reviews | P86: =VLOOKUP(O86,Sheet3!$A$1:$B$22,2,0) -> Review Analysis | Q86: Text | R86: No | S86: No | T86: No | U86: No | V86: Yes | W86: No | X86: Binary | Y86: Binary | Z86: Decide | AA86: Deep | AB86: Text | AC86: Binary | AD86: Deep | AE86: Human | AF86: No | AG86: HAI = Beer, Explain-Top-1 | AH86: Yes | AI86: Yes | AJ86: Image, Numeric, Text | AK86: Accuracy | AL86: Accuracy | AM86: Up | AN86: 462 | AO86: 92 | AP86: 88 | AQ86: Crowdworkers | AR86: Crowdworkers | AS86: MTurk | AT86: No | AU86: Yes | AV86: 0.8157 | AW86: 0.84 | AX86: 0.8852 | AY86: 0.8157 | AZ86: 0.84 | BA86: 0.8852 | BB86: AI | BC86: 0.84 | BD86: 0.8157 | BE86: 1 | BF86: 0.0914 | BG86: 0 | BH86: 0.0576 | BI86: 0 | BJ86: 0.0914 | BK86: No | BL86: HAI = Explain-Top-1
A87: Bansal_2021 | B87: 6 | C87: 1 | D87: 3 | E87: 1 | F87: 6.1 | G87: 6.1.3.1 | H87: Does the Whole Exceed Its Parts? The Effect of AI Explanations on Complementary Team Performance | I87: Bansal, Gagan; Wu, Tongshuang; Zhou, Joyce; Fok, Raymond; Nushi, Besmira; Kamar, Ece; Ribeiro, Marco Tulio; Weld, Daniel | J87: 2021 | K87: Communication | L87: Proceedings of the 2021 CHI Conference on Human Factors in Computing Systems | M87: Between-Subjects | N87: Independent Samples | O87: Classify beer reviews | P87: =VLOOKUP(O87,Sheet3!$A$1:$B$22,2,0) -> Review Analysis | Q87: Text | R87: No | S87: No | T87: No | U87: No | V87: Yes | W87: No | X87: Binary | Y87: Binary | Z87: Decide | AA87: Deep | AB87: Text | AC87: Binary | AD87: Deep | AE87: Human | AF87: No | AG87: HAI = Beer, Explain-Top-2 | AH87: Yes | AI87: Yes | AJ87: Image, Numeric, Text | AK87: Accuracy | AL87: Accuracy | AM87: Up | AN87: 462 | AO87: 92 | AP87: 92 | AQ87: Crowdworkers | AR87: Crowdworkers | AS87: MTurk | AT87: No | AU87: Yes | AV87: 0.8157 | AW87: 0.84 | AX87: 0.8786 | AY87: 0.8157 | AZ87: 0.84 | BA87: 0.8786 | BB87: AI | BC87: 0.84 | BD87: 0.8157 | BE87: 1 | BF87: 0.0914 | BG87: 0 | BH87: 0.0737 | BI87: 0 | BJ87: 0.0914 | BK87: No | BL87: HAI = Explain-Top-2
A88: Bansal_2021 | B88: 6 | C88: 1 | D88: 4 | E88: 1 | F88: 6.1 | G88: 6.1.4.1 | H88: Does the Whole Exceed Its Parts? The Effect of AI Explanations on Complementary Team Performance | I88: Bansal, Gagan; Wu, Tongshuang; Zhou, Joyce; Fok, Raymond; Nushi, Besmira; Kamar, Ece; Ribeiro, Marco Tulio; Weld, Daniel | J88: 2021 | K88: Communication | L88: Proceedings of the 2021 CHI Conference on Human Factors in Computing Systems | M88: Between-Subjects | N88: Independent Samples | O88: Classify beer reviews | P88: =VLOOKUP(O88,Sheet3!$A$1:$B$22,2,0) -> Review Analysis | Q88: Text | R88: No | S88: No | T88: No | U88: No | V88: Yes | W88: No | X88: Binary | Y88: Binary | Z88: Decide | AA88: Deep | AB88: Text | AC88: Binary | AD88: Deep | AE88: Human | AF88: No | AG88: HAI = Beer, Adaptive | AH88: Yes | AI88: Yes | AJ88: Image, Numeric, Text | AK88: Accuracy | AL88: Accuracy | AM88: Up | AN88: 462 | AO88: 92 | AP88: 98 | AQ88: Crowdworkers | AR88: Crowdworkers | AS88: MTurk | AT88: No | AU88: Yes | AV88: 0.8157 | AW88: 0.84 | AX88: 0.8869 | AY88: 0.8157 | AZ88: 0.84 | BA88: 0.8869 | BB88: AI | BC88: 0.84 | BD88: 0.8157 | BE88: 1 | BF88: 0.0914 | BG88: 0 | BH88: 0.054 | BI88: 0 | BJ88: 0.0914 | BK88: No | BL88: HAI = Adaptive
A89: Bansal_2021 | B89: 6 | C89: 2 | D89: 1 | E89: 1 | F89: 6.2 | G89: 6.2.1.1 | H89: Does the Whole Exceed Its Parts? The Effect of AI Explanations on Complementary Team Performance | I89: Bansal, Gagan; Wu, Tongshuang; Zhou, Joyce; Fok, Raymond; Nushi, Besmira; Kamar, Ece; Ribeiro, Marco Tulio; Weld, Daniel | J89: 2021 | K89: Communication | L89: Proceedings of the 2021 CHI Conference on Human Factors in Computing Systems | M89: Between-Subjects | N89: Independent Samples | O89: Classify Amazon reviews | P89: =VLOOKUP(O89,Sheet3!$A$1:$B$22,2,0) -> Review Analysis | Q89: Text | R89: No | S89: No | T89: No | U89: No | V89: Yes | W89: No | X89: Binary | Y89: Binary | Z89: Decide | AA89: Deep | AB89: Text | AC89: Binary | AD89: Deep | AE89: Human | AF89: No | AG89: HAI = Amazon, Conf | AH89: Yes | AI89: Yes | AJ89: Numeric | AK89: Accuracy | AL89: Accuracy | AM89: Up | AN89: 457 | AO89: 91 | AP89: 92 | AQ89: Crowdworkers | AR89: Crowdworkers | AS89: MTurk | AT89: No | AU89: Yes | AV89: 0.8769 | AW89: 0.84 | AX89: 0.9065 | AY89: 0.8769 | AZ89: 0.84 | BA89: 0.9065 | BB89: Human | BC89: 0.8769 | BD89: 0.84 | BE89: 1 | BF89: 0.1232 | BG89: 0 | BH89: 0.0691 | BI89: 0.12324988 | BJ89: 0 | BK89: No | BL89: HAI = Conf
A90: Bansal_2021 | B90: 6 | C90: 2 | D90: 2 | E90: 1 | F90: 6.2 | G90: 6.2.2.1 | H90: Does the Whole Exceed Its Parts? The Effect of AI Explanations on Complementary Team Performance | I90: Bansal, Gagan; Wu, Tongshuang; Zhou, Joyce; Fok, Raymond; Nushi, Besmira; Kamar, Ece; Ribeiro, Marco Tulio; Weld, Daniel | J90: 2021 | K90: Communication | L90: Proceedings of the 2021 CHI Conference on Human Factors in Computing Systems | M90: Between-Subjects | N90: Independent Samples | O90: Classify Amazon reviews | P90: =VLOOKUP(O90,Sheet3!$A$1:$B$22,2,0) -> Review Analysis | Q90: Text | R90: No | S90: No | T90: No | U90: No | V90: Yes | W90: No | X90: Binary | Y90: Binary | Z90: Decide | AA90: Deep | AB90: Text | AC90: Binary | AD90: Deep | AE90: Human | AF90: No | AG90: HAI = Amazon, Explain-Top-1 | AH90: Yes | AI90: Yes | AJ90: Image, Numeric, Text | AK90: Accuracy | AL90: Accuracy | AM90: Up | AN90: 457 | AO90: 91 | AP90: 91 | AQ90: Crowdworkers | AR90: Crowdworkers | AS90: MTurk | AT90: No | AU90: Yes | AV90: 0.8769 | AW90: 0.84 | AX90: 0.918 | AY90: 0.8769 | AZ90: 0.84 | BA90: 0.918 | BB90: Human | BC90: 0.8769 | BD90: 0.84 | BE90: 1 | BF90: 0.1232 | BG90: 0 | BH90: 0.0555 | BI90: 0.12324988 | BJ90: 0 | BK90: No | BL90: HAI = Explain-Top-1
A91: Bansal_2021 | B91: 6 | C91: 2 | D91: 3 | E91: 1 | F91: 6.2 | G91: 6.2.3.1 | H91: Does the Whole Exceed Its Parts? The Effect of AI Explanations on Complementary Team Performance | I91: Bansal, Gagan; Wu, Tongshuang; Zhou, Joyce; Fok, Raymond; Nushi, Besmira; Kamar, Ece; Ribeiro, Marco Tulio; Weld, Daniel | J91: 2021 | K91: Communication | L91: Proceedings of the 2021 CHI Conference on Human Factors in Computing Systems | M91: Between-Subjects | N91: Independent Samples | O91: Classify Amazon reviews | P91: =VLOOKUP(O91,Sheet3!$A$1:$B$22,2,0) -> Review Analysis | Q91: Text | R91: No | S91: No | T91: No | U91: No | V91: Yes | W91: No | X91: Binary | Y91: Binary | Z91: Decide | AA91: Deep | AB91: Text | AC91: Binary | AD91: Deep | AE91: Human | AF91: No | AG91: HAI = Amazon, Explain-Top-2 | AH91: Yes | AI91: Yes | AJ91: Image, Numeric, Text | AK91: Accuracy | AL91: Accuracy | AM91: Up | AN91: 457 | AO91: 91 | AP91: 90 | AQ91: Crowdworkers | AR91: Crowdworkers | AS91: MTurk | AT91: No | AU91: Yes | AV91: 0.8769 | AW91: 0.84 | AX91: 0.9096 | AY91: 0.8769 | AZ91: 0.84 | BA91: 0.9096 | BB91: Human | BC91: 0.8769 | BD91: 0.84 | BE91: 1 | BF91: 0.1232 | BG91: 0 | BH91: 0.0813 | BI91: 0.12324988 | BJ91: 0 | BK91: No | BL91: HAI = Explain-Top-2
A92: Bansal_2021 | B92: 6 | C92: 2 | D92: 4 | E92: 1 | F92: 6.2 | G92: 6.2.4.1 | H92: Does the Whole Exceed Its Parts? The Effect of AI Explanations on Complementary Team Performance | I92: Bansal, Gagan; Wu, Tongshuang; Zhou, Joyce; Fok, Raymond; Nushi, Besmira; Kamar, Ece; Ribeiro, Marco Tulio; Weld, Daniel | J92: 2021 | K92: Communication | L92: Proceedings of the 2021 CHI Conference on Human Factors in Computing Systems | M92: Between-Subjects | N92: Independent Samples | O92: Classify Amazon reviews | P92: =VLOOKUP(O92,Sheet3!$A$1:$B$22,2,0) -> Review Analysis | Q92: Text | R92: No | S92: No | T92: No | U92: No | V92: Yes | W92: No | X92: Binary | Y92: Binary | Z92: Decide | AA92: Deep | AB92: Text | AC92: Binary | AD92: Deep | AE92: Human | AF92: No | AG92: HAI = Amazon, Adaptive | AH92: Yes | AI92: Yes | AJ92: Image, Numeric, Text | AK92: Accuracy | AL92: Accuracy | AM92: Up | AN92: 457 | AO92: 91 | AP92: 93 | AQ92: Crowdworkers | AR92: Crowdworkers | AS92: MTurk | AT92: No | AU92: Yes | AV92: 0.8769 | AW92: 0.84 | AX92: 0.9172 | AY92: 0.8769 | AZ92: 0.84 | BA92: 0.9172 | BB92: Human | BC92: 0.8769 | BD92: 0.84 | BE92: 1 | BF92: 0.1232 | BG92: 0 | BH92: 0.0648 | BI92: 0.12324988 | BJ92: 0 | BK92: No | BL92: HAI = Adaptive
A93: Gao_2021 | B93: 8 | C93: 1 | D93: 1 | E93: 1 | F93: 8.1 | G93: 8.1.1.1 | H93: Evaluating Human-AI Hybrid Conversational Systems with Chatbot Message Suggestions | I93: Gao, Zihan; Jiang, Jiepu | J93: 2021 | K93: Communication | L93: Proceedings of the 30th ACM International Conference on Information &amp; Knowledge Management | M93: Between-Subjects | N93: Independent Samples | O93: Engage in a conversation | P93: =VLOOKUP(O93,Sheet3!$A$1:$B$22,2,0) -> Customer Service | Q93: Text | R93: No | S93: No | T93: No | U93: No | V93: Yes | W93: No | X93: Text | Y93: Open Response | Z93: Create | AA93: Deep | AB93: Text | AC93: Text | AD93: Deep | AE93: Human | AF93: No | AG93: HAI = RetWiki | AH93: No | AI93: No | AK93: Quality | AL93: Quality | AM93: Up | AN93: 1050 | AO93: 50 | AP93: 300 | AQ93: Crowdworkers | AR93: Crowdworkers | AS93: MTurk | AT93: No | AU93: Yes | AV93: 3.74 | AW93: 3.68 | AX93: 3.77 | AY93: 3.74 | AZ93: 3.68 | BA93: 3.77 | BB93: Human | BC93: 3.74 | BD93: 3.68 | BE93: 1 | BF93: 0.73 | BG93: 0.71 | BH93: 0.68 | BI93: 0.73 | BJ93: 0.71 | BK93: No | BL93: HAI = RetWiki
A94: Gao_2021 | B94: 8 | C94: 1 | D94: 2 | E94: 1 | F94: 8.1 | G94: 8.1.2.1 | H94: Evaluating Human-AI Hybrid Conversational Systems with Chatbot Message Suggestions | I94: Gao, Zihan; Jiang, Jiepu | J94: 2021 | K94: Communication | L94: Proceedings of the 30th ACM International Conference on Information &amp; Knowledge Management | M94: Between-Subjects | N94: Independent Samples | O94: Engage in a conversation | P94: =VLOOKUP(O94,Sheet3!$A$1:$B$22,2,0) -> Customer Service | Q94: Text | R94: No | S94: No | T94: No | U94: No | V94: Yes | W94: No | X94: Text | Y94: Open Response | Z94: Create | AA94: Deep | AB94: Text | AC94: Text | AD94: Deep | AE94: Human | AF94: No | AG94: HAI = RetBest | AH94: No | AI94: No | AK94: Quality | AL94: Quality | AM94: Up | AN94: 1050 | AO94: 50 | AP94: 300 | AQ94: Crowdworkers | AR94: Crowdworkers | AS94: MTurk | AT94: No | AU94: Yes | AV94: 3.74 | AW94: 3.87 | AX94: 3.89 | AY94: 3.74 | AZ94: 3.87 | BA94: 3.89 | BB94: AI | BC94: 3.87 | BD94: 3.74 | BE94: 1 | BF94: 0.73 | BG94: 0.66 | BH94: 0.65 | BI94: 0.66 | BJ94: 0.73 | BK94: No | BL94: HAI = RetBest
A95: Gao_2021 | B95: 8 | C95: 1 | D95: 3 | E95: 1 | F95: 8.1 | G95: 8.1.3.1 | H95: Evaluating Human-AI Hybrid Conversational Systems with Chatbot Message Suggestions | I95: Gao, Zihan; Jiang, Jiepu | J95: 2021 | K95: Communication | L95: Proceedings of the 30th ACM International Conference on Information &amp; Knowledge Management | M95: Between-Subjects | N95: Independent Samples | O95: Engage in a conversation | P95: =VLOOKUP(O95,Sheet3!$A$1:$B$22,2,0) -> Customer Service | Q95: Text | R95: No | S95: No | T95: No | U95: No | V95: Yes | W95: No | X95: Text | Y95: Open Response | Z95: Create | AA95: Deep | AB95: Text | AC95: Text | AD95: Deep | AE95: Human | AF95: No | AG95: HAI = RetWorst | AH95: No | AI95: No | AK95: Quality | AL95: Quality | AM95: Up | AN95: 1050 | AO95: 50 | AP95: 300 | AQ95: Crowdworkers | AR95: Crowdworkers | AS95: MTurk | AT95: No | AU95: Yes | AV95: 3.74 | AW95: 2.84 | AX95: 3.35 | AY95: 3.74 | AZ95: 2.84 | BA95: 3.35 | BB95: Human | BC95: 3.74 | BD95: 2.84 | BE95: 0 | BF95: 0.73 | BG95: 0.9 | BH95: 0.87 | BI95: 0.73 | BJ95: 0.9 | BK95: No | BL95: HAI = RetWorst
A96: Gao_2021 | B96: 8 | C96: 1 | D96: 4 | E96: 1 | F96: 8.1 | G96: 8.1.4.1 | H96: Evaluating Human-AI Hybrid Conversational Systems with Chatbot Message Suggestions | I96: Gao, Zihan; Jiang, Jiepu | J96: 2021 | K96: Communication | L96: Proceedings of the 30th ACM International Conference on Information &amp; Knowledge Management | M96: Between-Subjects | N96: Independent Samples | O96: Engage in a conversation | P96: =VLOOKUP(O96,Sheet3!$A$1:$B$22,2,0) -> Customer Service | Q96: Text | R96: No | S96: No | T96: No | U96: No | V96: Yes | W96: No | X96: Text | Y96: Open Response | Z96: Create | AA96: Deep | AB96: Text | AC96: Text | AD96: Deep | AE96: Human | AF96: No | AG96: HAI = RetWorst | AH96: No | AI96: No | AK96: Quality | AL96: Quality | AM96: Up | AN96: 1050 | AO96: 50 | AP96: 100 | AQ96: Crowdworkers | AR96: Crowdworkers | AS96: MTurk | AT96: No | AU96: Yes | AV96: 3.74 | AW96: 3.1 | AX96: 3.43 | AY96: 3.74 | AZ96: 3.1 | BA96: 3.43 | BB96: Human | BC96: 3.74 | BD96: 3.1 | BE96: 0 | BF96: 0.73 | BG96: 0.83 | BH96: 0.82 | BI96: 0.73 | BJ96: 0.83 | BK96: No | BL96: HAI = RetWorst
A97: Lai_2022b | B97: 10 | C97: 1 | D97: 1 | E97: 1 | F97: 10.1 | G97: 10.1.1.1 | H97: Human-AI Collaboration via Conditional Delegation: A Case Study of Content Moderation | I97: Lai, Vivian; Carton, Samuel; Bhatnagar, Rajat; Liao, Q. Vera; Zhang, Yunfeng; Tan, Chenhao | J97: 2022 | K97: Communication | L97: Proceedings of the 2022 CHI Conference on Human Factors in Computing Systems | M97: Between-Subjects | N97: Independent Samples | O97: Moderate content | P97: Customer Service | Q97: Text | R97: No | S97: No | T97: No | U97: No | V97: Yes | W97: No | X97: Text | Y97: Open Response | Z97: Create | AA97: Deep | AB97: Text | AC97: Text | AD97: Deep | AE97: Human | AF97: No | AG97: WikiAttack, HAI = Predicted labels | AH97: Yes | AI97: No | AJ97: Text | AK97: Precision | AL97: Accuracy | AM97: Up | AN97: 120 | AO97: 30 | AP97: 30 | AQ97: Crowdworkers | AR97: Crowdworkers | AS97: MTurk | AT97: No | AU97: Yes | AV97: 0.788 | AW97: 0.89 | AX97: 0.94 | AY97: 0.788 | AZ97: 0.89 | BA97: 0.94 | BB97: AI | BC97: 0.89 | BD97: 0.788 | BE97: 1 | BF97: 0.1726 | BG97: 0 | BH97: 0.036636066 | BI97: 0.1726 | BJ97: 0.1726 | BK97: No | BL97: Reddit, HAI = Predicted labels + local explanations
A98: Lai_2022b | B98: 10 | C98: 1 | D98: 2 | E98: 1 | F98: 10.1 | G98: 10.1.2.1 | H98: Human-AI Collaboration via Conditional Delegation: A Case Study of Content Moderation | I98: Lai, Vivian; Carton, Samuel; Bhatnagar, Rajat; Liao, Q. Vera; Zhang, Yunfeng; Tan, Chenhao | J98: 2022 | K98: Communication | L98: Proceedings of the 2022 CHI Conference on Human Factors in Computing Systems | M98: Between-Subjects | N98: Independent Samples | O98: Moderate content | P98: Customer Service | Q98: Text | R98: No | S98: No | T98: No | U98: No | V98: Yes | W98: No | X98: Text | Y98: Open Response | Z98: Create | AA98: Deep | AB98: Text | AC98: Text | AD98: Deep | AE98: Human | AF98: No | AG98: WikiAttack, HAI = Predicted labels + local explanations | AH98: Yes | AI98: No | AJ98: Text | AK98: Precision | AL98: Accuracy | AM98: Up | AN98: 120 | AO98: 30 | AP98: 30 | AQ98: Crowdworkers | AR98: Crowdworkers | AS98: MTurk | AT98: No | AU98: Yes | AV98: 0.788 | AW98: 0.89 | AX98: 0.932 | AY98: 0.788 | AZ98: 0.89 | BA98: 0.932 | BB98: AI | BC98: 0.89 | BD98: 0.788 | BE98: 1 | BF98: 0.1726 | BG98: 0 | BH98: 0.048295427 | BI98: 0.1726 | BJ98: 0.1726 | BK98: No | BL98: Reddit, HAI = Predicted labels + local explanations + global explanations
A99: Lai_2022b | B99: 10 | C99: 1 | D99: 3 | E99: 1 | F99: 10.1 | G99: 10.1.3.1 | H99: Human-AI Collaboration via Conditional Delegation: A Case Study of Content Moderation | I99: Lai, Vivian; Carton, Samuel; Bhatnagar, Rajat; Liao, Q. Vera; Zhang, Yunfeng; Tan, Chenhao | J99: 2022 | K99: Communication | L99: Proceedings of the 2022 CHI Conference on Human Factors in Computing Systems | M99: Between-Subjects | N99: Independent Samples | O99: Moderate content | P99: Customer Service | Q99: Text | R99: No | S99: No | T99: No | U99: No | V99: Yes | W99: No | X99: Text | Y99: Open Response | Z99: Create | AA99: Deep | AB99: Text | AC99: Text | AD99: Deep | AE99: Human | AF99: No | AG99: WikiAttack, HAI = Predicted labels + local explanations + global explanations | AH99: Yes | AI99: No | AJ99: Text | AK99: Precision | AL99: Accuracy | AM99: Up | AN99: 120 | AO99: 30 | AP99: 30 | AQ99: Crowdworkers | AR99: Crowdworkers | AS99: MTurk | AT99: No | AU99: Yes | AV99: 0.788 | AW99: 0.89 | AX99: 0.948 | AY99: 0.788 | AZ99: 0.89 | BA99: 0.948 | BB99: AI | BC99: 0.89 | BD99: 0.788 | BE99: 1 | BF99: 0.1726 | BG99: 0 | BH99: 0.024976705 | BI99: 0.1726 | BJ99: 0.1726 | BK99: No | BL99: No tutorial, with xai
A100: Lai_2022b | B100: 10 | C100: 2 | D100: 1 | E100: 1 | F100: 10.2 | G100: 10.2.1.1 | H100: Human-AI Collaboration via Conditional Delegation: A Case Study of Content Moderation | I100: Lai, Vivian; Carton, Samuel; Bhatnagar, Rajat; Liao, Q. Vera; Zhang, Yunfeng; Tan, Chenhao | J100: 2022 | K100: Communication | L100: Proceedings of the 2022 CHI Conference on Human Factors in Computing Systems | M100: Between-Subjects | N100: Independent Samples | O100: Moderate content | P100: Customer Service | Q100: Text | R100: No | S100: No | T100: No | U100: No | V100: Yes | W100: No | X100: Text | Y100: Open Response | Z100: Create | AA100: Deep | AB100: Text | AC100: Text | AD100: Deep | AE100: Human | AF100: No | AG100: Reddit, HAI = Predicted labels | AH100: Yes | AI100: No | AJ100: Text | AK100: Precision | AL100: Accuracy | AM100: Up | AN100: 120 | AO100: 30 | AP100: 30 | AQ100: Crowdworkers | AR100: Crowdworkers | AS100: MTurk | AT100: No | AU100: Yes | AV100: 0.628 | AW100: 0.54 | AX100: 0.626 | AY100: 0.628 | AZ100: 0.54 | BA100: 0.626 | BB100: Human | BC100: 0.628 | BD100: 0.54 | BE100: 0 | BF100: 0.1324 | BG100: 0 | BH100: 0.082302897 | BI100: 0.628 | BJ100: 0 | BK100: No | BL100: With tutorial, with xai
...

Sheet Sheet3
A1: Task_Desc | B1: Marketing-Related Task Category
A2: Predict housing prices | B2: Demand Forecasting
A3: Forecast demand | B3: Demand Forecasting
A4: Plan a route | B4: Demand Forecasting
A5: Predict basketball games | B5: Demand Forecasting
A6: Predicting behavioral science study outcomes | B6: Demand Forecasting
A7: Predict a person’s profession | B7: Customer Segmentation
A8: Determine if person’s income exceeds $50,000 | B8: Customer Segmentation
A9: Sort recyclables | B9: Review Analysis
A10: Classify toxic comments | B10: Review Analysis
A11: Classify beer reviews | B11: Review Analysis
A12: Classify Amazon reviews | B12: Review Analysis
... A22: Answer LSAT questions | B22: Customer Service

Sheet Sheet2
A3: Row Labels | B3: Count of Title | F3: Paper_Name | G3: =VLOOKUP(F3,$A$4:$B$31,2,0) -> #N/A
A4: Bansal_2021 | B4: 12 | F4: Poursabzi-Sangdeh_2021 | G4: =VLOOKUP(F4,$A$4:$B$31,2,0) -> 12
A5: Bondi_2022 | B5: 3 | F5: Bansal_2021 | G5: =VLOOKUP(F5,$A$4:$B$31,2,0) -> 12
A6: Cabrera_2023 | B6: 2 | F6: Kyriacou_2021 | G6: =VLOOKUP(F6,$A$4:$B$31,2,0) -> 1
A7: Carton_2020 | B7: 15 | F7: Liu_2021 | G7: =VLOOKUP(F7,$A$4:$B$31,2,0) -> 4
A8: Chen_2023 | B8: 4 | F8: Ma_2023 | G8: =VLOOKUP(F8,$A$4:$B$31,2,0) -> 4
A9: Desmond_2021 | B9: 2 | F9: Lehmann_2022 | G9: =VLOOKUP(F9,$A$4:$B$31,2,0) -> 3
A10: Elder_2022 | B10: 6 | F10: Skirzynski_2021 | G10: =VLOOKUP(F10,$A$4:$B$31,2,0) -> 3
A11: Gao_2021 | B11: 4 | F11: Hemmer_2022 | G11: =VLOOKUP(F11,$A$4:$B$31,2,0) -> 1
A12: Groh_2022 | B12: 2 | F12: Chen_2023 | G12: =VLOOKUP(F12,$A$4:$B$31,2,0) -> 4
A13: Hemmer_2022 | B13: 1 | F13: Elder_2022 | G13: =VLOOKUP(F13,$A$4:$B$31,2,0) -> 6
A14: Jiang_2020 | B14: 6 | F14: Bondi_2022 | G14: =VLOOKUP(F14,$A$4:$B$31,2,0) -> 3
A15: Kyriacou_2021 | B15: 1 | F15: Lu_Peng_2024 | G15: =VLOOKUP(F15,$A$4:$B$31,2,0) -> 1
... A30: Vodrahalli_2022 | B30: 5 | F30: Vodrahalli_2022 | G30: =VLOOKUP(F30,$A$4:$B$31,2,0) -> 5
A31: (blank)
A32: Grand Total | B32: 132

Sheet Sheet1
A1: Paper_Name | B1: Paper_ID | C1: Exp_ID | D1: Treatment_ID | E1: Measure_ID | F1: Exp_ID_Cleaned | G1: ES_ID | H1: Title | I1: Authors | J1: Year | K1: Venue | L1: Exp_Design | M1: Comp_Type | N1: Task_Desc | O1: Task_Data | P1: Task_Data_Cleaned
A2: Poursabzi-Sangdeh_2021 | B2: 5 | C2: 1 | D2: 1 | E2: 1 | F2: 5.1 | G2: 5.1.1.1 | H2: Manipulating and Measuring Model Interpretability | I2: Poursabzi-Sangdeh, Forough; Goldstein, Daniel G; Hofman, Jake M; Wortman Vaughan, Jennifer Wortman; Wallach, Hanna | J2: 2021 | K2: Proceedings of the 2021 CHI Conference on Human Factors in Computing Systems | L2: Mixed, Between-Subjects | M2: Independent Samples | N2: Predict housing prices | O2: Numeric | P2: Numeric
A3: Bansal_2021 | B3: 6 | C3: 3 | D3: 1 | E3: 1 | F3: 6.3 | G3: 6.3.1.1 | H3: Does the Whole Exceed Its Parts? The Effect of AI Explanations on Complementary Team Performance | I3: Bansal, Gagan; Wu, Tongshuang; Zhou, Joyce; Fok, Raymond; Nushi, Besmira; Kamar, Ece; Ribeiro, Marco Tulio; Weld, Daniel | J3: 2021 | K3: Proceedings of the 2021 CHI Conference on Human Factors in Computing Systems | L3: Between-Subjects | M3: Independent Samples | N3: Answer LSAT questions | O3: Text | P3: Text
A4: Kyriacou_2021 | B4: 7 | C4: 1 | D4: 2 | E4: 1 | F4: 7.1 | G4: 7.1.2.1 | H4: Learning to Work in a Materials Recovery Facility: Can Humans and Machines Learn from Each Other? | I4: Kyriacou, Harrison; Ramakrishnan, Anand; Whitehill, Jacob | J4: 2021 | K4: LAK21: 11th International Learning Analytics and Knowledge Conference | L4: Between-Subjects | M4: Independent Samples | N4: Sort recyclables | O4: Image | P4: Image
A5: Liu_2021 | B5: 9 | C5: 2 | D5: 1 | E5: 1 | F5: 9.2 | G5: 9.2.1.1 | H5: Understanding the Effect of Out-of-Distribution Examples and Interactive Explanations on Human-AI Decision Making | I5: Liu, Han; Lai, Vivian; Tan, Chenhao | J5: 2021 | K5: Proc. ACM Hum.-Comput. Interact. | L5: Between-Subjects | M5: Independent Samples | N5: Predict a person's profession | O5: Text | P5: Text
A6: Ma_2023 | B6: 14 | C6: 1 | D6: 1 | E6: 1 | F6: 14.1 | G6: 14.1.1.1 | H6: Who Should I Trust: AI or Myself? Leveraging Human and AI Correctness Likelihood to Promote Appropriate Trust in AI-Assisted Decision-Making | I6: Ma, Shuai; Lei, Ying; Wang, Xinru; Zheng, Chengbo; Shi, Chuhan; Yin, Ming; Ma, Xiaojuan | J6: 2023 | K6: Proceedings of the 2023 CHI Conference on Human Factors in Computing Systems | L6: Between-Subjects | M6: Independent Samples | N6: Determine if person's income exceeds $50,000 | O6: Categoric, Numeric | P6: Multiple
A7: Lehmann_2022 | B7: 20 | C7: 1 | D7: 1 | E7: 1 | F7: 20.1 | G7: 20.1.1.1 | H7: The risk of algorithm transparency: How algorithm complexity drives the effects on the use of advice | I7: Lehmann, Cedric A.; Haubitz, Christiane B.; Fuegener, Andreas; Thonemann, Ulrich W. | J7: 2022 | K7: Production and Operations Management | L7: Mixed, Within-Subjects | M7: Dependent Samples | N7: Forecast demand | O7: Numeric | P7: Numeric
A8: Skirzynski_2021 | B8: 27 | C8: 1 | D8: 1 | E8: 1 | F8: 27.1 | G8: 27.1.1.1 | H8: Automatic discovery of interpretable planning strategies | I8: Skirzynski, J; Becker, F; Lieder, F | J8: 2021 | K8: Machine Learning | L8: Between-Subjects | M8: Independent Samples | N8: Plan a route | O8: Numeric | P8: Numeric
A9: Hemmer_2022 | B9: 68 | C9: 1 | D9: 2 | E9: 1 | F9: 68.1 | G9: 68.1.2.1 | H9: On the effect of information asymmetry in human-AI teams | I9: Hemmer, Patrick; Schemmer, Max; KÃ¼hl, Niklas; VÃ¶ssing, Michael; Satzger, Gerhard | J9: 2022 | K9: CHI Conference on Human Factors in Computing Systems (CHI â€™22), Workshop on Human-Centered Explainable AI (HCXAI) | L9: Between-Subjects | M9: Independent Samples | N9: Predict housing prices | O9: Categoric, Numeric | P9: Multiple
A10: Chen_2023 | B10: 69 | C10: 1 | D10: 1 | E10: 1 | F10: 69.1 | G10: 69.1.1.1 | H10: Understanding the role of human intuition on reliance in human-AI decision-making with explanations | I10: Chen, Valerie; Liao, Q. Vera; Vaughan, Jennifer Wortman; Bansal, Gagan | J10: 2023 | K10: CSCW 2023 | L10: Within-Subjects | M10: Dependent Samples | N10: Predict housing prices | O10: Categoric, Numeric | P10: Multiple
A11: Elder_2022 | B11: 72 | C11: 1 | D11: 1 | E11: 1 | F11: 72.1 | G11: 72.1.1.1 | H11: Knowing when to pass: The effect of AI reliability in risky decision contexts | I11: Elder, Hannah; Canfield, Casey; Shank, Daniel B.; Rieger, Tobias; Hines, Casey | J11: 2022 | K11: Human Factors | L11: Between-Subjects | M11: Independent Samples | N11: Predict basketball games | O11: Numeric | P11: Numeric
A12: Bondi_2022 | B12: 74 | C12: 1 | D12: 1 | E12: 1 | F12: 74.1 | G12: 74.1.1.1 | H12: Role of human-AI interaction in selective prediction | I12: Bondi, Elizabeth; Koster, Raphael; Sheahan, Hannah; Chadwick, Martin; Bachrach, Yoram; Cemgil, Taylan; Paquet, Ulrich; Dvijotham, Krishnamurthy | J12: 2022 | K12: Proceedings of the AAAI Conference on Artificial Intelligence | L12: Within-Subjects | M12: Dependent Samples | N12: Detect animal in image | O12: Image | P12: Image
A13: Lu_Peng_2024 | B13: 84 | C13: 4 | D13: 1 | E13: 1 | F13: 4.1 | G13: Lu_Peng_2024_1 | H13: Human-AI Collaboration: Unraveling the Effects of User Proficiency and AI Agent Capability in Intelligent Decision Support Systems | I13: Lu Peng, Xiangbin Yan, Yunan Hu, Xin Luo | J13: 2024 | K13: Decision Support Systems | L13: Between-subjects | M13: Dependent Samples | N13: Decision-making accuracy in an AI-assisted decision support system | O13: Text | P13: Image
... A27: Lippert_2024 | B27: 81 | C27: 1 | D27: 1 | E27: 1 | F27: 1.1 | G27: Lippert_2024_1 | H27: Can Large Language Models Help Predict Results from a Complex Behavioural Science Study? | I27: Lippert, Steffen; Dreber, Anna; Johannesson, Magnus; Tierney, Warren; Cyrus-Lai, Wilson; Uhlmann, Eric Luis; Pfeiffer, Thomas | J27: 2024 | K27: Royal Society Open Science | L27: Between-subjects | M27: Dependent Samples | N27: Predicting behavioral science study outcomes | O27: Text | P27: Text
A28: Vodrahalli_2022 | B28: 67 | C28: 1 | D28: 1 | E28: 1 | F28: 67.1 | G28: 79.1.1.1 | H28: Do humans trust advice more if it comes from AI? An analysis of human-AI interactions | I28: Vodrahalli, Kailas; Daneshjou, Roxana; Gerstenberg, Tobias; Zou, James | J28: 2022 | L28: Within-Subjects | M28: Dependent Samples | O28: Image | P28: Image
